{
  "resolvedId": "/Users/yunhao/Project/website/components/Footer.vue?vue&type=style&index=0&scoped=62d380ff&lang.css?inline&used",
  "transforms": [
    {
      "name": "vite:vue",
      "result": "\n.footer-stack {\n  /* height: 380px; */\n}\n.footer {\n  z-index: 20000;\n  bottom: 0;\n  /* position: fixed; */\n  width: 100%;\n  height: auto;\n  background-color: #0c1829;\n  .content {\n    display: flex;\n    border-bottom: 1px solid #c1c7cd;\n    .item {\n      margin: 2rem;\n      color: #ffffff;\n      font-weight: lighter;\n      .title {\n        font-weight: bold;\n        color: white;\n        font-size: 18px;\n        margin-bottom: 1rem;\n      }\n      .link {\n        margin: 4px 0px;\n      }\n    }\n  }\n  .footer-text {\n    color: white;\n    display: flex;\n    flex-direction: column;\n    justify-content: center;\n    align-items: center;\n  }\n}\n@media (max-width: 991px) {\n  .footer {\n    .content {\n      display: flex;\n      flex-direction: column;\n      .item {\n        margin: 0.5rem 1rem 0.5rem 1rem;\n        border-bottom: 1px solid white;\n        .link {\n          margin-bottom: 1rem;\n        }\n      }\n      .item-desk {\n        border-bottom: 0px solid white !important;\n      }\n    }\n  }\n}\n",
      "start": 1756100544075,
      "end": 1756100544075,
      "sourcemaps": {
        "version": 3,
        "sources": [
          "/Users/yunhao/Project/website/components/Footer.vue"
        ],
        "names": [],
        "mappings": ";AAqCA,CAAC,CAAC,CAAC,CAAC,CAAC,CAAC,CAAC,CAAC,CAAC,CAAC,CAAC,CAAC,EAAE;EACZ,CAAC,EAAE,CAAC,CAAC,CAAC,CAAC,CAAC,CAAC,EAAE,CAAC,CAAC,CAAC,CAAC,CAAC,EAAE,CAAC;AACrB;AACA,CAAC,CAAC,CAAC,CAAC,CAAC,CAAC,EAAE;EACN,CAAC,CAAC,CAAC,CAAC,CAAC,CAAC,CAAC,EAAE,CAAC,CAAC,CAAC,CAAC,CAAC;EACd,CAAC,CAAC,CAAC,CAAC,CAAC,CAAC,EAAE,CAAC;EACT,CAAC,EAAE,CAAC,CAAC,CAAC,CAAC,CAAC,CAAC,CAAC,CAAC,EAAE,CAAC,CAAC,CAAC,CAAC,CAAC,EAAE,CAAC;EACrB,CAAC,CAAC,CAAC,CAAC,CAAC,EAAE,CAAC,CAAC,CAAC,CAAC;EACX,CAAC,CAAC,CAAC,CAAC,CAAC,CAAC,EAAE,CAAC,CAAC,CAAC,CAAC;EACZ,CAAC,CAAC,CAAC,CAAC,CAAC,CAAC,CAAC,CAAC,CAAC,CAAC,CAAC,CAAC,CAAC,CAAC,CAAC,CAAC,EAAE,CAAC,CAAC,CAAC,CAAC,CAAC,CAAC,CAAC;EACzB,CAAC,CAAC,CAAC,CAAC,CAAC,CAAC,CAAC,EAAE;IACP,CAAC,CAAC,CAAC,CAAC,CAAC,CAAC,CAAC,EAAE,CAAC,CAAC,CAAC,CAAC;IACb,CAAC,CAAC,CAAC,CAAC,CAAC,CAAC,CAAC,CAAC,CAAC,CAAC,CAAC,CAAC,CAAC,EAAE,CAAC,CAAC,EAAE,CAAC,CAAC,CAAC,CAAC,EAAE,CAAC,CAAC,CAAC,CAAC,CAAC,CAAC,CAAC;IAChC,CAAC,CAAC,CAAC,CAAC,EAAE;MACJ,CAAC,CAAC,CAAC,CAAC,CAAC,CAAC,EAAE,CAAC,CAAC,CAAC,CAAC;MACZ,CAAC,CAAC,CAAC,CAAC,CAAC,EAAE,CAAC,CAAC,CAAC,CAAC,CAAC,CAAC,CAAC;MACd,CAAC,CAAC,CAAC,CAAC,CAAC,CAAC,CAAC,CAAC,CAAC,CAAC,CAAC,EAAE,CAAC,CAAC,CAAC,CAAC,CAAC,CAAC,CAAC;MACpB,CAAC,CAAC,CAAC,CAAC,CAAC,EAAE;QACL,CAAC,CAAC,CAAC,CAAC,CAAC,CAAC,CAAC,CAAC,CAAC,CAAC,CAAC,EAAE,CAAC,CAAC,CAAC,CAAC;QACjB,CAAC,CAAC,CAAC,CAAC,CAAC,EAAE,CAAC,CAAC,CAAC,CAAC,CAAC;QACZ,CAAC,CAAC,CAAC,CAAC,CAAC,CAAC,CAAC,CAAC,CAAC,EAAE,CAAC,CAAC,CAAC,CAAC;QACf,CAAC,CAAC,CAAC,CAAC,CAAC,CAAC,CAAC,CAAC,CAAC,CAAC,CAAC,CAAC,CAAC,EAAE,CAAC,CAAC,CAAC,CAAC;MACrB;MACA,CAAC,CAAC,CAAC,CAAC,EAAE;QACJ,CAAC,CAAC,CAAC,CAAC,CAAC,CAAC,EAAE,CAAC,CAAC,EAAE,CAAC,CAAC,CAAC;MACjB;IACF;EACF;EACA,CAAC,CAAC,CAAC,CAAC,CAAC,CAAC,CAAC,CAAC,CAAC,CAAC,CAAC,EAAE;IACX,CAAC,CAAC,CAAC,CAAC,CAAC,EAAE,CAAC,CAAC,CAAC,CAAC,CAAC;IACZ,CAAC,CAAC,CAAC,CAAC,CAAC,CAAC,CAAC,EAAE,CAAC,CAAC,CAAC,CAAC;IACb,CAAC,CAAC,CAAC,CAAC,CAAC,CAAC,CAAC,CAAC,CAAC,CAAC,CAAC,CAAC,CAAC,CAAC,EAAE,CAAC,CAAC,CAAC,CAAC,CAAC,CAAC;IACtB,CAAC,CAAC,CAAC,CAAC,CAAC,CAAC,CAAC,CAAC,CAAC,CAAC,CAAC,CAAC,CAAC,CAAC,CAAC,EAAE,CAAC,CAAC,CAAC,CAAC,CAAC,CAAC;IACvB,CAAC,CAAC,CAAC,CAAC,CAAC,CAAC,CAAC,CAAC,CAAC,CAAC,CAAC,EAAE,CAAC,CAAC,CAAC,CAAC,CAAC,CAAC;EACrB;AACF;AACA,CAAC,CAAC,CAAC,CAAC,CAAC,EAAE,CAAC,CAAC,CAAC,CAAC,CAAC,CAAC,CAAC,CAAC,CAAC,CAAC,EAAE,CAAC,CAAC,CAAC,CAAC,CAAC,EAAE;EACxB,CAAC,CAAC,CAAC,CAAC,CAAC,CAAC,EAAE;IACN,CAAC,CAAC,CAAC,CAAC,CAAC,CAAC,CAAC,EAAE;MACP,CAAC,CAAC,CAAC,CAAC,CAAC,CAAC,CAAC,EAAE,CAAC,CAAC,CAAC,CAAC;MACb,CAAC,CAAC,CAAC,CAAC,CAAC,CAAC,CAAC,CAAC,CAAC,CAAC,CAAC,CAAC,CAAC,CAAC,EAAE,CAAC,CAAC,CAAC,CAAC,CAAC,CAAC;MACtB,CAAC,CAAC,CAAC,CAAC,EAAE;QACJ,CAAC,CAAC,CAAC,CAAC,CAAC,CAAC,EAAE,CAAC,CAAC,CAAC,CAAC,CAAC,EAAE,CAAC,CAAC,CAAC,EAAE,CAAC,CAAC,CAAC,CAAC,CAAC,EAAE,CAAC,CAAC,CAAC,CAAC;QAC/B,CAAC,CAAC,CAAC,CAAC,CAAC,CAAC,CAAC,CAAC,CAAC,CAAC,CAAC,CAAC,CAAC,EAAE,CAAC,CAAC,EAAE,CAAC,CAAC,CAAC,CAAC,EAAE,CAAC,CAAC,CAAC,CAAC,CAAC;QAC9B,CAAC,CAAC,CAAC,CAAC,EAAE;UACJ,CAAC,CAAC,CAAC,CAAC,CAAC,CAAC,CAAC,CAAC,CAAC,CAAC,CAAC,CAAC,CAAC,EAAE,CAAC,CAAC,CAAC,CAAC;QACrB;MACF;MACA,CAAC,CAAC,CAAC,CAAC,CAAC,CAAC,CAAC,CAAC,CAAC,EAAE;QACT,CAAC,CAAC,CAAC,CAAC,CAAC,CAAC,CAAC,CAAC,CAAC,CAAC,CAAC,CAAC,CAAC,EAAE,CAAC,CAAC,EAAE,CAAC,CAAC,CAAC,CAAC,EAAE,CAAC,CAAC,CAAC,CAAC,EAAE,CAAC,CAAC,CAAC,CAAC,CAAC,CAAC,CAAC,CAAC,CAAC,CAAC;MAC3C;IACF;EACF;AACF",
        "file": "/Users/yunhao/Project/website/components/Footer.vue",
        "sourceRoot": "",
        "sourcesContent": [
          "<template>\n  <div class=\"footer-stack\"></div>\n  <div class=\"footer\">\n    <div class=\"content container\">\n      <!-- <div class=\"item\"><img src=\"@/assets/img/LOGO_udigit_2.png\" alt=\"\" /></div> -->\n      <div class=\"item\">\n        <div class=\"title\">重點專案</div>\n        <div class=\"link\">全家記帳本</div>\n        <div class=\"link\">去你的工作室</div>\n        <div class=\"link\">電商網站(工作前)</div>\n        <div class=\"link\">個人網站(工作前)</div>\n      </div>\n      <div class=\"item\">\n        <div class=\"title\">工作經歷</div>\n        <div class=\"link\">慎行科技 23.12-25.08</div>\n      </div>\n      <div class=\"item\">\n        <div class=\"title\">關於我</div>\n        <div class=\"link\">個人簡介</div>\n      </div>\n      <div class=\"item\">\n        <div class=\"title\">聯絡資訊</div>\n        <div class=\"link\">地址：<span style=\"font-weight: bold\">台北市信義區XXX</span></div>\n        <div class=\"link\">電話：<span style=\"font-weight: bold\">09 0978 6383</span></div>\n      </div>\n      <div class=\"item item-desk\">\n        <div class=\"title\">社群平台</div>\n        <div><img src=\"@/assets/img/facebook.png\" alt=\"\" style=\"margin-right: 1rem\" /> <img src=\"@/assets/img/linkedin.png\" alt=\"\" /></div>\n      </div>\n    </div>\n    <div class=\"footer-text py-2\">\n      <div>此為個人練習作品 無商業用途</div>\n      <div>2025.09</div>\n    </div>\n  </div>\n</template>\n<style scoped>\n.footer-stack {\n  /* height: 380px; */\n}\n.footer {\n  z-index: 20000;\n  bottom: 0;\n  /* position: fixed; */\n  width: 100%;\n  height: auto;\n  background-color: #0c1829;\n  .content {\n    display: flex;\n    border-bottom: 1px solid #c1c7cd;\n    .item {\n      margin: 2rem;\n      color: #ffffff;\n      font-weight: lighter;\n      .title {\n        font-weight: bold;\n        color: white;\n        font-size: 18px;\n        margin-bottom: 1rem;\n      }\n      .link {\n        margin: 4px 0px;\n      }\n    }\n  }\n  .footer-text {\n    color: white;\n    display: flex;\n    flex-direction: column;\n    justify-content: center;\n    align-items: center;\n  }\n}\n@media (max-width: 991px) {\n  .footer {\n    .content {\n      display: flex;\n      flex-direction: column;\n      .item {\n        margin: 0.5rem 1rem 0.5rem 1rem;\n        border-bottom: 1px solid white;\n        .link {\n          margin-bottom: 1rem;\n        }\n      }\n      .item-desk {\n        border-bottom: 0px solid white !important;\n      }\n    }\n  }\n}\n</style>\n"
        ]
      }
    },
    {
      "name": "nuxt:layer-aliasing",
      "start": 1756100544076,
      "end": 1756100544076,
      "order": "pre"
    },
    {
      "name": "nuxt:layer-aliasing",
      "start": 1756100544076,
      "end": 1756100544076,
      "order": "pre"
    },
    {
      "name": "nuxt:server-devonly:transform",
      "start": 1756100544076,
      "end": 1756100544076,
      "order": "pre"
    },
    {
      "name": "nuxt:server-devonly:transform",
      "start": 1756100544076,
      "end": 1756100544076,
      "order": "pre"
    },
    {
      "name": "nuxt:client-fallback-auto-id",
      "start": 1756100544076,
      "end": 1756100544076,
      "order": "pre"
    },
    {
      "name": "server-only-component-transform",
      "start": 1756100544076,
      "end": 1756100544076,
      "order": "pre"
    },
    {
      "name": "vite:css",
      "result": ".footer{background-color:#0c1829;bottom:0;height:auto;width:100%;z-index:20000;.content{border-bottom:1px solid #c1c7cd;display:flex;.item{color:#fff;font-weight:lighter;margin:2rem;.title{color:#fff;font-size:18px;font-weight:700;margin-bottom:1rem}.link{margin:4px 0}}}.footer-text{align-items:center;color:#fff;display:flex;flex-direction:column;justify-content:center}}@media (max-width:991px){.footer{.content{display:flex;flex-direction:column;.item{border-bottom:1px solid #fff;margin:.5rem 1rem;.link{margin-bottom:1rem}}.item-desk{border-bottom:0 solid #fff!important}}}}",
      "start": 1756100544076,
      "end": 1756100544080,
      "order": "normal",
      "sourcemaps": {
        "file": "/Users/yunhao/Project/website/components/Footer.vue",
        "mappings": "AAIA,QAME,wBAAyB,CAJzB,QAAS,CAGT,WAAY,CADZ,UAAW,CAHX,aAAc,CAMd,SAEE,+BAAgC,CADhC,YAAa,CAEb,MAEE,UAAc,CACd,mBAAoB,CAFpB,WAAY,CAGZ,OAEE,UAAY,CACZ,cAAe,CAFf,eAAiB,CAGjB,kBACF,CACA,MACE,YACF,CACF,CACF,CACA,aAKE,kBAAmB,CAJnB,UAAY,CACZ,YAAa,CACb,qBAAsB,CACtB,sBAEF,CACF,CACA,yBACE,QACE,SACE,YAAa,CACb,qBAAsB,CACtB,MAEE,4BAA8B,CAD9B,iBAA+B,CAE/B,MACE,kBACF,CACF,CACA,WACE,oCACF,CACF,CACF,CACF",
        "names": [],
        "sources": [
          "/Users/yunhao/Project/website/components/Footer.vue"
        ],
        "sourcesContent": [
          "\n.footer-stack {\n  /* height: 380px; */\n}\n.footer {\n  z-index: 20000;\n  bottom: 0;\n  /* position: fixed; */\n  width: 100%;\n  height: auto;\n  background-color: #0c1829;\n  .content {\n    display: flex;\n    border-bottom: 1px solid #c1c7cd;\n    .item {\n      margin: 2rem;\n      color: #ffffff;\n      font-weight: lighter;\n      .title {\n        font-weight: bold;\n        color: white;\n        font-size: 18px;\n        margin-bottom: 1rem;\n      }\n      .link {\n        margin: 4px 0px;\n      }\n    }\n  }\n  .footer-text {\n    color: white;\n    display: flex;\n    flex-direction: column;\n    justify-content: center;\n    align-items: center;\n  }\n}\n@media (max-width: 991px) {\n  .footer {\n    .content {\n      display: flex;\n      flex-direction: column;\n      .item {\n        margin: 0.5rem 1rem 0.5rem 1rem;\n        border-bottom: 1px solid white;\n        .link {\n          margin-bottom: 1rem;\n        }\n      }\n      .item-desk {\n        border-bottom: 0px solid white !important;\n      }\n    }\n  }\n}\n"
        ],
        "version": 3
      }
    },
    {
      "name": "vite:esbuild",
      "start": 1756100544080,
      "end": 1756100544080,
      "order": "normal"
    },
    {
      "name": "vite:json",
      "start": 1756100544080,
      "end": 1756100544080,
      "order": "normal"
    },
    {
      "name": "vite:worker",
      "start": 1756100544081,
      "end": 1756100544081,
      "order": "normal"
    },
    {
      "name": "vite:vue",
      "result": ".footer{&[data-v-62d380ff]{background-color:#0c1829;bottom:0;height:auto;width:100%;z-index:20000}.content{&[data-v-62d380ff]{border-bottom:1px solid #c1c7cd;display:flex}.item{&[data-v-62d380ff]{color:#fff;font-weight:lighter;margin:2rem}.title[data-v-62d380ff]{color:#fff;font-size:18px;font-weight:700;margin-bottom:1rem}.link[data-v-62d380ff]{margin:4px 0}}}.footer-text[data-v-62d380ff]{align-items:center;color:#fff;display:flex;flex-direction:column;justify-content:center}}@media (max-width:991px){.footer{.content{&[data-v-62d380ff]{display:flex;flex-direction:column}.item{&[data-v-62d380ff]{border-bottom:1px solid #fff;margin:.5rem 1rem}.link[data-v-62d380ff]{margin-bottom:1rem}}.item-desk[data-v-62d380ff]{border-bottom:0 solid #fff!important}}}}",
      "start": 1756100544081,
      "end": 1756100544082,
      "order": "normal",
      "sourcemaps": {
        "file": "/Users/yunhao/Project/website/components/Footer.vue",
        "mappings": "AAAA,QCAA,mBDAQ,wBAAwB,CAAC,QAAQ,CAAC,WAAW,CAAC,UAAU,CAAC,cCAjE,ADA+E,SCA/E,mBDAwF,+BAA+B,CAAC,aCAxH,ADAqI,MCArI,mBDA2I,UAAU,CAAC,mBAAmB,CAAC,YCA1K,ADAsL,wBAAO,UAAU,CAAC,cAAc,CAAC,eAAe,CAAC,kBAAkB,CAAC,uBAAM,YAAY,CAAC,CAAC,CAAC,8BAAa,kBAAkB,CAAC,UAAU,CAAC,YAAY,CAAC,qBAAqB,CAAC,sBAAsB,CAAC,CAAC,yBAAyB,QAAQ,SCAtZ,mBDA+Z,YAAY,CAAC,sBCA5a,ADAkc,MCAlc,mBDAwc,4BAA4B,CAAC,kBCAre,ADAuf,uBAAM,kBAAkB,CAAC,CAAC,4BAAW,oCAAoC,CAAC,CAAC,CAAC",
        "names": [],
        "sources": [
          "/Users/yunhao/Project/website/components/Footer.vue",
          "\u0000<no source>"
        ],
        "sourcesContent": [
          null,
          null
        ],
        "version": 3
      }
    },
    {
      "name": "vite:vue-jsx",
      "start": 1756100544082,
      "end": 1756100544082,
      "order": "normal"
    },
    {
      "name": "replace",
      "start": 1756100544082,
      "end": 1756100544082,
      "order": "normal"
    },
    {
      "name": "replace",
      "start": 1756100544082,
      "end": 1756100544082,
      "order": "normal"
    },
    {
      "name": "nuxt:remove-plugin-metadata",
      "start": 1756100544082,
      "end": 1756100544082,
      "order": "normal"
    },
    {
      "name": "nuxt:remove-plugin-metadata",
      "start": 1756100544082,
      "end": 1756100544082,
      "order": "normal"
    },
    {
      "name": "nuxt:components:imports",
      "start": 1756100544082,
      "end": 1756100544082,
      "order": "normal"
    },
    {
      "name": "replace",
      "start": 1756100544082,
      "end": 1756100544082,
      "order": "normal"
    },
    {
      "name": "ssr-styles",
      "start": 1756100544082,
      "end": 1756100544082,
      "order": "normal"
    },
    {
      "name": "vite:define",
      "start": 1756100544082,
      "end": 1756100544082,
      "order": "normal"
    },
    {
      "name": "vite:css-post",
      "result": "export default \".footer{&[data-v-62d380ff]{background-color:#0c1829;bottom:0;height:auto;width:100%;z-index:20000}.content{&[data-v-62d380ff]{border-bottom:1px solid #c1c7cd;display:flex}.item{&[data-v-62d380ff]{color:#fff;font-weight:lighter;margin:2rem}.title[data-v-62d380ff]{color:#fff;font-size:18px;font-weight:700;margin-bottom:1rem}.link[data-v-62d380ff]{margin:4px 0}}}.footer-text[data-v-62d380ff]{align-items:center;color:#fff;display:flex;flex-direction:column;justify-content:center}}@media (max-width:991px){.footer{.content{&[data-v-62d380ff]{display:flex;flex-direction:column}.item{&[data-v-62d380ff]{border-bottom:1px solid #fff;margin:.5rem 1rem}.link[data-v-62d380ff]{margin-bottom:1rem}}.item-desk[data-v-62d380ff]{border-bottom:0 solid #fff!important}}}}\"",
      "start": 1756100544082,
      "end": 1756100544083,
      "order": "normal",
      "sourcemaps": {
        "mappings": ""
      }
    },
    {
      "name": "vite:build-html",
      "start": 1756100544083,
      "end": 1756100544083,
      "order": "normal"
    },
    {
      "name": "vite:worker-import-meta-url",
      "start": 1756100544083,
      "end": 1756100544083,
      "order": "normal"
    },
    {
      "name": "vite:asset-import-meta-url",
      "start": 1756100544083,
      "end": 1756100544083,
      "order": "normal"
    },
    {
      "name": "commonjs",
      "start": 1756100544083,
      "end": 1756100544083,
      "order": "normal"
    },
    {
      "name": "vite:dynamic-import-vars",
      "start": 1756100544083,
      "end": 1756100544083,
      "order": "normal"
    },
    {
      "name": "vite:import-glob",
      "start": 1756100544083,
      "end": 1756100544083,
      "order": "normal"
    },
    {
      "name": "nuxt:composable-keys",
      "start": 1756100544083,
      "end": 1756100544083,
      "order": "post"
    },
    {
      "name": "nuxt:composable-keys",
      "start": 1756100544083,
      "end": 1756100544083,
      "order": "post"
    },
    {
      "name": "unplugin-vue-components",
      "result": "/* unplugin-vue-components disabled */export default \".footer{&[data-v-62d380ff]{background-color:#0c1829;bottom:0;height:auto;width:100%;z-index:20000}.content{&[data-v-62d380ff]{border-bottom:1px solid #c1c7cd;display:flex}.item{&[data-v-62d380ff]{color:#fff;font-weight:lighter;margin:2rem}.title[data-v-62d380ff]{color:#fff;font-size:18px;font-weight:700;margin-bottom:1rem}.link[data-v-62d380ff]{margin:4px 0}}}.footer-text[data-v-62d380ff]{align-items:center;color:#fff;display:flex;flex-direction:column;justify-content:center}}@media (max-width:991px){.footer{.content{&[data-v-62d380ff]{display:flex;flex-direction:column}.item{&[data-v-62d380ff]{border-bottom:1px solid #fff;margin:.5rem 1rem}.link[data-v-62d380ff]{margin-bottom:1rem}}.item-desk[data-v-62d380ff]{border-bottom:0 solid #fff!important}}}}\"",
      "start": 1756100544083,
      "end": 1756100544083,
      "order": "post",
      "sourcemaps": {
        "version": 3,
        "sources": [
          "/Users/yunhao/Project/website/components/Footer.vue?vue&type=style&index=0&scoped=62d380ff&lang.css?inline&used"
        ],
        "sourcesContent": [
          "export default \".footer{&[data-v-62d380ff]{background-color:#0c1829;bottom:0;height:auto;width:100%;z-index:20000}.content{&[data-v-62d380ff]{border-bottom:1px solid #c1c7cd;display:flex}.item{&[data-v-62d380ff]{color:#fff;font-weight:lighter;margin:2rem}.title[data-v-62d380ff]{color:#fff;font-size:18px;font-weight:700;margin-bottom:1rem}.link[data-v-62d380ff]{margin:4px 0}}}.footer-text[data-v-62d380ff]{align-items:center;color:#fff;display:flex;flex-direction:column;justify-content:center}}@media (max-width:991px){.footer{.content{&[data-v-62d380ff]{display:flex;flex-direction:column}.item{&[data-v-62d380ff]{border-bottom:1px solid #fff;margin:.5rem 1rem}.link[data-v-62d380ff]{margin-bottom:1rem}}.item-desk[data-v-62d380ff]{border-bottom:0 solid #fff!important}}}}\""
        ],
        "names": [],
        "mappings": "sCAAA,MAAM,CAAC,OAAO,CAAC,CAAC,CAAC,MAAM,CAAC,CAAC,CAAC,IAAI,CAAC,CAAC,CAAC,QAAQ,CAAC,CAAC,UAAU,CAAC,KAAK,CAAC,CAAC,MAAM,CAAC,MAAM,CAAC,CAAC,CAAC,MAAM,CAAC,IAAI,CAAC,KAAK,CAAC,GAAG,CAAC,CAAC,CAAC,CAAC,KAAK,CAAC,KAAK,CAAC,CAAC,OAAO,CAAC,CAAC,CAAC,IAAI,CAAC,CAAC,CAAC,QAAQ,CAAC,CAAC,MAAM,CAAC,MAAM,CAAC,GAAG,CAAC,KAAK,CAAC,CAAC,MAAM,CAAC,OAAO,CAAC,IAAI,CAAC,CAAC,IAAI,CAAC,CAAC,CAAC,IAAI,CAAC,CAAC,CAAC,QAAQ,CAAC,CAAC,KAAK,CAAC,CAAC,GAAG,CAAC,IAAI,CAAC,MAAM,CAAC,OAAO,CAAC,MAAM,CAAC,IAAI,CAAC,CAAC,KAAK,CAAC,IAAI,CAAC,CAAC,CAAC,QAAQ,CAAC,CAAC,KAAK,CAAC,CAAC,GAAG,CAAC,IAAI,CAAC,IAAI,CAAC,IAAI,CAAC,IAAI,CAAC,MAAM,CAAC,GAAG,CAAC,MAAM,CAAC,MAAM,CAAC,IAAI,CAAC,CAAC,IAAI,CAAC,IAAI,CAAC,CAAC,CAAC,QAAQ,CAAC,CAAC,MAAM,CAAC,GAAG,CAAC,CAAC,CAAC,CAAC,CAAC,CAAC,MAAM,CAAC,IAAI,CAAC,IAAI,CAAC,CAAC,CAAC,QAAQ,CAAC,CAAC,KAAK,CAAC,KAAK,CAAC,MAAM,CAAC,KAAK,CAAC,CAAC,GAAG,CAAC,OAAO,CAAC,IAAI,CAAC,IAAI,CAAC,SAAS,CAAC,MAAM,CAAC,OAAO,CAAC,OAAO,CAAC,MAAM,CAAC,CAAC,CAAC,KAAK,CAAC,CAAC,GAAG,CAAC,KAAK,CAAC,KAAK,CAAC,CAAC,CAAC,MAAM,CAAC,CAAC,OAAO,CAAC,CAAC,CAAC,IAAI,CAAC,CAAC,CAAC,QAAQ,CAAC,CAAC,OAAO,CAAC,IAAI,CAAC,IAAI,CAAC,SAAS,CAAC,MAAM,CAAC,CAAC,IAAI,CAAC,CAAC,CAAC,IAAI,CAAC,CAAC,CAAC,QAAQ,CAAC,CAAC,MAAM,CAAC,MAAM,CAAC,GAAG,CAAC,KAAK,CAAC,CAAC,GAAG,CAAC,MAAM,CAAC,CAAC,IAAI,CAAC,IAAI,CAAC,CAAC,IAAI,CAAC,IAAI,CAAC,CAAC,CAAC,QAAQ,CAAC,CAAC,MAAM,CAAC,MAAM,CAAC,IAAI,CAAC,CAAC,CAAC,IAAI,CAAC,IAAI,CAAC,IAAI,CAAC,CAAC,CAAC,QAAQ,CAAC,CAAC,MAAM,CAAC,MAAM,CAAC,CAAC,CAAC,KAAK,CAAC,CAAC,GAAG,CAAC,SAAS,CAAC,CAAC,CAAC,CAAC"
      }
    },
    {
      "name": "unplugin-vue-components",
      "result": "/* unplugin-vue-components disabled */export default \".footer{&[data-v-62d380ff]{background-color:#0c1829;bottom:0;height:auto;width:100%;z-index:20000}.content{&[data-v-62d380ff]{border-bottom:1px solid #c1c7cd;display:flex}.item{&[data-v-62d380ff]{color:#fff;font-weight:lighter;margin:2rem}.title[data-v-62d380ff]{color:#fff;font-size:18px;font-weight:700;margin-bottom:1rem}.link[data-v-62d380ff]{margin:4px 0}}}.footer-text[data-v-62d380ff]{align-items:center;color:#fff;display:flex;flex-direction:column;justify-content:center}}@media (max-width:991px){.footer{.content{&[data-v-62d380ff]{display:flex;flex-direction:column}.item{&[data-v-62d380ff]{border-bottom:1px solid #fff;margin:.5rem 1rem}.link[data-v-62d380ff]{margin-bottom:1rem}}.item-desk[data-v-62d380ff]{border-bottom:0 solid #fff!important}}}}\"",
      "start": 1756100544083,
      "end": 1756100544083,
      "order": "post",
      "sourcemaps": {
        "version": 3,
        "sources": [
          "/Users/yunhao/Project/website/components/Footer.vue?vue&type=style&index=0&scoped=62d380ff&lang.css?inline&used"
        ],
        "sourcesContent": [
          "export default \".footer{&[data-v-62d380ff]{background-color:#0c1829;bottom:0;height:auto;width:100%;z-index:20000}.content{&[data-v-62d380ff]{border-bottom:1px solid #c1c7cd;display:flex}.item{&[data-v-62d380ff]{color:#fff;font-weight:lighter;margin:2rem}.title[data-v-62d380ff]{color:#fff;font-size:18px;font-weight:700;margin-bottom:1rem}.link[data-v-62d380ff]{margin:4px 0}}}.footer-text[data-v-62d380ff]{align-items:center;color:#fff;display:flex;flex-direction:column;justify-content:center}}@media (max-width:991px){.footer{.content{&[data-v-62d380ff]{display:flex;flex-direction:column}.item{&[data-v-62d380ff]{border-bottom:1px solid #fff;margin:.5rem 1rem}.link[data-v-62d380ff]{margin-bottom:1rem}}.item-desk[data-v-62d380ff]{border-bottom:0 solid #fff!important}}}}\""
        ],
        "names": [],
        "mappings": "sCAAA,MAAM,CAAC,OAAO,CAAC,CAAC,CAAC,MAAM,CAAC,CAAC,CAAC,IAAI,CAAC,CAAC,CAAC,QAAQ,CAAC,CAAC,UAAU,CAAC,KAAK,CAAC,CAAC,MAAM,CAAC,MAAM,CAAC,CAAC,CAAC,MAAM,CAAC,IAAI,CAAC,KAAK,CAAC,GAAG,CAAC,CAAC,CAAC,CAAC,KAAK,CAAC,KAAK,CAAC,CAAC,OAAO,CAAC,CAAC,CAAC,IAAI,CAAC,CAAC,CAAC,QAAQ,CAAC,CAAC,MAAM,CAAC,MAAM,CAAC,GAAG,CAAC,KAAK,CAAC,CAAC,MAAM,CAAC,OAAO,CAAC,IAAI,CAAC,CAAC,IAAI,CAAC,CAAC,CAAC,IAAI,CAAC,CAAC,CAAC,QAAQ,CAAC,CAAC,KAAK,CAAC,CAAC,GAAG,CAAC,IAAI,CAAC,MAAM,CAAC,OAAO,CAAC,MAAM,CAAC,IAAI,CAAC,CAAC,KAAK,CAAC,IAAI,CAAC,CAAC,CAAC,QAAQ,CAAC,CAAC,KAAK,CAAC,CAAC,GAAG,CAAC,IAAI,CAAC,IAAI,CAAC,IAAI,CAAC,IAAI,CAAC,MAAM,CAAC,GAAG,CAAC,MAAM,CAAC,MAAM,CAAC,IAAI,CAAC,CAAC,IAAI,CAAC,IAAI,CAAC,CAAC,CAAC,QAAQ,CAAC,CAAC,MAAM,CAAC,GAAG,CAAC,CAAC,CAAC,CAAC,CAAC,CAAC,MAAM,CAAC,IAAI,CAAC,IAAI,CAAC,CAAC,CAAC,QAAQ,CAAC,CAAC,KAAK,CAAC,KAAK,CAAC,MAAM,CAAC,KAAK,CAAC,CAAC,GAAG,CAAC,OAAO,CAAC,IAAI,CAAC,IAAI,CAAC,SAAS,CAAC,MAAM,CAAC,OAAO,CAAC,OAAO,CAAC,MAAM,CAAC,CAAC,CAAC,KAAK,CAAC,CAAC,GAAG,CAAC,KAAK,CAAC,KAAK,CAAC,CAAC,CAAC,MAAM,CAAC,CAAC,OAAO,CAAC,CAAC,CAAC,IAAI,CAAC,CAAC,CAAC,QAAQ,CAAC,CAAC,OAAO,CAAC,IAAI,CAAC,IAAI,CAAC,SAAS,CAAC,MAAM,CAAC,CAAC,IAAI,CAAC,CAAC,CAAC,IAAI,CAAC,CAAC,CAAC,QAAQ,CAAC,CAAC,MAAM,CAAC,MAAM,CAAC,GAAG,CAAC,KAAK,CAAC,CAAC,GAAG,CAAC,MAAM,CAAC,CAAC,IAAI,CAAC,IAAI,CAAC,CAAC,IAAI,CAAC,IAAI,CAAC,CAAC,CAAC,QAAQ,CAAC,CAAC,MAAM,CAAC,MAAM,CAAC,IAAI,CAAC,CAAC,CAAC,IAAI,CAAC,IAAI,CAAC,IAAI,CAAC,CAAC,CAAC,QAAQ,CAAC,CAAC,MAAM,CAAC,MAAM,CAAC,CAAC,CAAC,KAAK,CAAC,CAAC,GAAG,CAAC,SAAS,CAAC,CAAC,CAAC,CAAC"
      }
    },
    {
      "name": "nuxt:imports-transform",
      "start": 1756100544083,
      "end": 1756100544083,
      "order": "post"
    },
    {
      "name": "nuxt:imports-transform",
      "start": 1756100544083,
      "end": 1756100544083,
      "order": "post"
    },
    {
      "name": "unctx:transform",
      "start": 1756100544083,
      "end": 1756100544083,
      "order": "post"
    },
    {
      "name": "unctx:transform",
      "start": 1756100544083,
      "end": 1756100544083,
      "order": "post"
    },
    {
      "name": "nuxt:pages-macros-transform",
      "start": 1756100544083,
      "end": 1756100544083,
      "order": "post"
    },
    {
      "name": "nuxt:pages-macros-transform",
      "start": 1756100544083,
      "end": 1756100544083,
      "order": "post"
    },
    {
      "name": "element-plus:transform",
      "start": 1756100544083,
      "end": 1756100544083,
      "order": "post"
    },
    {
      "name": "vant:transform",
      "start": 1756100544083,
      "end": 1756100544083,
      "order": "post"
    },
    {
      "name": "nuxt:tree-shake-template",
      "start": 1756100544083,
      "end": 1756100544083,
      "order": "post"
    },
    {
      "name": "nuxt:components-loader",
      "start": 1756100544083,
      "end": 1756100544083,
      "order": "post"
    },
    {
      "name": "nuxt:tree-shake-composables:transform",
      "start": 1756100544083,
      "end": 1756100544083,
      "order": "post"
    },
    {
      "name": "vite:build-import-analysis",
      "start": 1756100544083,
      "end": 1756100544083,
      "order": "normal"
    },
    {
      "name": "vite:reporter",
      "start": 1756100544083,
      "end": 1756100544083,
      "order": "normal"
    }
  ]
}
