{
  "resolvedId": "/Users/yunhao/Project/website/pages/tongxin-xili-web/index.vue",
  "transforms": [
    {
      "name": "vite:load-fallback",
      "result": "<template>\n  <Navbar />\n  <div id=\"projectPage\">\n    <div class=\"container\">\n      <div class=\"title\">協力國際形象網站 <img @click=\"openWeb()\" style=\"cursor: pointer\" src=\"@/assets/img/link.png\" alt=\"\" /></div>\n      <div class=\"title-m\">協力國際管理顧問有限公司</div>\n      <div class=\"d-flex justify-content-center mt-3\">\n        <div class=\"main-img\">\n          <div class=\"main-border\">\n            <div class=\"second-border\">\n              <img src=\"@/assets/img/tongxin1.png\" alt=\"\" />\n            </div>\n          </div>\n        </div>\n      </div>\n      <div class=\"background\">\n        <div class=\"title mt-5 mb-3\">專案背景</div>\n        <div class=\"content\">本專案旨在為協力國際管理顧問有限公司打造一個形象網站．</div>\n      </div>\n      <div class=\"skill\">\n        <div class=\"title\">技術應用</div>\n        <ul style=\"margin-left: 2rem; margin-top: 1rem\">\n          <li>使用：html、css、JavaScript、Swiper、AOS、BootStrap</li>\n        </ul>\n      </div>\n      <div class=\"otherImg\">\n        <img src=\"@/assets/img/tongxin2.png\" alt=\"\" />\n      </div>\n      <div class=\"otherImg\">\n        <img src=\"@/assets/img/tongxin3.png\" alt=\"\" />\n      </div>\n      <div class=\"otherImg\">\n        <img src=\"@/assets/img/tongxin4.png\" alt=\"\" />\n      </div>\n      <div class=\"otherImg\">\n        <img src=\"@/assets/img/tongxin5.png\" alt=\"\" />\n      </div>\n    </div>\n  </div>\n  <Footer />\n</template>\n<script setup>\nconst openWeb = () => {\n  window.open(\"https://www.tongxin-xili.com.tw/\");\n};\n</script>\n<style scoped>\n.navbarStack {\n  height: 84px;\n  background-color: black;\n}\n</style>\n",
      "start": 1756100541892,
      "end": 1756100542052,
      "sourcemaps": null
    },
    {
      "name": "nuxt:layer-aliasing",
      "start": 1756100542052,
      "end": 1756100542052,
      "order": "pre"
    },
    {
      "name": "nuxt:layer-aliasing",
      "start": 1756100542052,
      "end": 1756100542052,
      "order": "pre"
    },
    {
      "name": "nuxt:server-devonly:transform",
      "start": 1756100542052,
      "end": 1756100542052,
      "order": "pre"
    },
    {
      "name": "nuxt:server-devonly:transform",
      "start": 1756100542052,
      "end": 1756100542052,
      "order": "pre"
    },
    {
      "name": "nuxt:client-fallback-auto-id",
      "start": 1756100542052,
      "end": 1756100542052,
      "order": "pre"
    },
    {
      "name": "server-only-component-transform",
      "start": 1756100542052,
      "end": 1756100542052,
      "order": "pre"
    },
    {
      "name": "vite:css",
      "start": 1756100542052,
      "end": 1756100542052,
      "order": "normal"
    },
    {
      "name": "vite:esbuild",
      "start": 1756100542052,
      "end": 1756100542052,
      "order": "normal"
    },
    {
      "name": "vite:json",
      "start": 1756100542052,
      "end": 1756100542052,
      "order": "normal"
    },
    {
      "name": "vite:worker",
      "start": 1756100542052,
      "end": 1756100542052,
      "order": "normal"
    },
    {
      "name": "vite:vue",
      "result": "import { resolveComponent as _resolveComponent } from \"vue\"\nimport { ssrRenderComponent as _ssrRenderComponent, ssrRenderStyle as _ssrRenderStyle, ssrRenderAttr as _ssrRenderAttr } from \"vue/server-renderer\"\nimport _imports_0 from '@/assets/img/link.png'\nimport _imports_1 from '@/assets/img/tongxin1.png'\nimport _imports_2 from '@/assets/img/tongxin2.png'\nimport _imports_3 from '@/assets/img/tongxin3.png'\nimport _imports_4 from '@/assets/img/tongxin4.png'\nimport _imports_5 from '@/assets/img/tongxin5.png'\n\n\n\nconst _sfc_main = {\n  __name: 'index',\n  __ssrInlineRender: true,\n  setup(__props) {\n\nconst openWeb = () => {\n  window.open(\"https://www.tongxin-xili.com.tw/\");\n};\n\nreturn (_ctx, _push, _parent, _attrs) => {\n  const _component_Navbar = _resolveComponent(\"Navbar\")\n  const _component_Footer = _resolveComponent(\"Footer\")\n\n  _push(`<!--[-->`)\n  _push(_ssrRenderComponent(_component_Navbar, null, null, _parent))\n  _push(`<div id=\"projectPage\" data-v-11a9daba><div class=\"container\" data-v-11a9daba><div class=\"title\" data-v-11a9daba>協力國際形象網站 <img style=\"${\n    _ssrRenderStyle({\"cursor\":\"pointer\"})\n  }\"${\n    _ssrRenderAttr(\"src\", _imports_0)\n  } alt=\"\" data-v-11a9daba></div><div class=\"title-m\" data-v-11a9daba>協力國際管理顧問有限公司</div><div class=\"d-flex justify-content-center mt-3\" data-v-11a9daba><div class=\"main-img\" data-v-11a9daba><div class=\"main-border\" data-v-11a9daba><div class=\"second-border\" data-v-11a9daba><img${\n    _ssrRenderAttr(\"src\", _imports_1)\n  } alt=\"\" data-v-11a9daba></div></div></div></div><div class=\"background\" data-v-11a9daba><div class=\"title mt-5 mb-3\" data-v-11a9daba>專案背景</div><div class=\"content\" data-v-11a9daba>本專案旨在為協力國際管理顧問有限公司打造一個形象網站．</div></div><div class=\"skill\" data-v-11a9daba><div class=\"title\" data-v-11a9daba>技術應用</div><ul style=\"${\n    _ssrRenderStyle({\"margin-left\":\"2rem\",\"margin-top\":\"1rem\"})\n  }\" data-v-11a9daba><li data-v-11a9daba>使用：html、css、JavaScript、Swiper、AOS、BootStrap</li></ul></div><div class=\"otherImg\" data-v-11a9daba><img${\n    _ssrRenderAttr(\"src\", _imports_2)\n  } alt=\"\" data-v-11a9daba></div><div class=\"otherImg\" data-v-11a9daba><img${\n    _ssrRenderAttr(\"src\", _imports_3)\n  } alt=\"\" data-v-11a9daba></div><div class=\"otherImg\" data-v-11a9daba><img${\n    _ssrRenderAttr(\"src\", _imports_4)\n  } alt=\"\" data-v-11a9daba></div><div class=\"otherImg\" data-v-11a9daba><img${\n    _ssrRenderAttr(\"src\", _imports_5)\n  } alt=\"\" data-v-11a9daba></div></div></div>`)\n  _push(_ssrRenderComponent(_component_Footer, null, null, _parent))\n  _push(`<!--]-->`)\n}\n}\n\n}\n\n\nimport \"/Users/yunhao/Project/website/pages/tongxin-xili-web/index.vue?vue&type=style&index=0&scoped=11a9daba&lang.css\"\n\nimport { useSSRContext as __vite_useSSRContext } from 'vue'\nconst _sfc_setup = _sfc_main.setup\n_sfc_main.setup = (props, ctx) => {\n  const ssrContext = __vite_useSSRContext()\n  ;(ssrContext.modules || (ssrContext.modules = new Set())).add(\"pages/tongxin-xili-web/index.vue\")\n  return _sfc_setup ? _sfc_setup(props, ctx) : undefined\n}\nimport _export_sfc from '\u0000plugin-vue:export-helper'\nexport default /*#__PURE__*/_export_sfc(_sfc_main, [['__scopeId',\"data-v-11a9daba\"]])",
      "start": 1756100542052,
      "end": 1756100542052,
      "order": "normal",
      "sourcemaps": {
        "version": 3,
        "sources": [
          "/Users/yunhao/Project/website/pages/tongxin-xili-web/index.vue"
        ],
        "sourcesContent": [
          "<template>\n  <Navbar />\n  <div id=\"projectPage\">\n    <div class=\"container\">\n      <div class=\"title\">協力國際形象網站 <img @click=\"openWeb()\" style=\"cursor: pointer\" src=\"@/assets/img/link.png\" alt=\"\" /></div>\n      <div class=\"title-m\">協力國際管理顧問有限公司</div>\n      <div class=\"d-flex justify-content-center mt-3\">\n        <div class=\"main-img\">\n          <div class=\"main-border\">\n            <div class=\"second-border\">\n              <img src=\"@/assets/img/tongxin1.png\" alt=\"\" />\n            </div>\n          </div>\n        </div>\n      </div>\n      <div class=\"background\">\n        <div class=\"title mt-5 mb-3\">專案背景</div>\n        <div class=\"content\">本專案旨在為協力國際管理顧問有限公司打造一個形象網站．</div>\n      </div>\n      <div class=\"skill\">\n        <div class=\"title\">技術應用</div>\n        <ul style=\"margin-left: 2rem; margin-top: 1rem\">\n          <li>使用：html、css、JavaScript、Swiper、AOS、BootStrap</li>\n        </ul>\n      </div>\n      <div class=\"otherImg\">\n        <img src=\"@/assets/img/tongxin2.png\" alt=\"\" />\n      </div>\n      <div class=\"otherImg\">\n        <img src=\"@/assets/img/tongxin3.png\" alt=\"\" />\n      </div>\n      <div class=\"otherImg\">\n        <img src=\"@/assets/img/tongxin4.png\" alt=\"\" />\n      </div>\n      <div class=\"otherImg\">\n        <img src=\"@/assets/img/tongxin5.png\" alt=\"\" />\n      </div>\n    </div>\n  </div>\n  <Footer />\n</template>\n<script setup>\nconst openWeb = () => {\n  window.open(\"https://www.tongxin-xili.com.tw/\");\n};\n</script>\n<style scoped>\n.navbarStack {\n  height: 84px;\n  background-color: black;\n}\n</style>\n"
        ],
        "names": [],
        "mappings": ";;;;;;;;;;;;;;;AAyCc;AACd,CAAC,CAAC,CAAC,CAAC,CAAC,CAAC,CAAC,CAAC,CAAC,CAAC,CAAC,CAAC,CAAC,CAAC,CAAC,CAAC,CAAC,CAAC,CAAC,CAAC,CAAC,CAAC,CAAC;AACvB,CAAC,CAAC,CAAC,CAAC,CAAC,CAAC,CAAC,CAAC,CAAC,CAAC,CAAC,CAAC,CAAC,CAAC,CAAC,CAAC,CAAC,CAAC,CAAC,CAAC,CAAC,CAAC,CAAC,CAAC,CAAC,CAAC,CAAC,CAAC,CAAC,CAAC,CAAC,CAAC,CAAC,CAAC,CAAC,CAAC,CAAC,CAAC,CAAC,CAAC,CAAC,CAAC,CAAC,CAAC,CAAC,CAAC,CAAC,CAAC,CAAC,CAAC;AAClD,CAAC,CAAC;;;;;;;;;;;;;;;;;;;;;;;;;;;;;;"
      }
    },
    {
      "name": "vite:vue-jsx",
      "start": 1756100542053,
      "end": 1756100542053,
      "order": "normal"
    },
    {
      "name": "replace",
      "start": 1756100542053,
      "end": 1756100542053,
      "order": "normal"
    },
    {
      "name": "replace",
      "start": 1756100542053,
      "end": 1756100542053,
      "order": "normal"
    },
    {
      "name": "nuxt:remove-plugin-metadata",
      "start": 1756100542053,
      "end": 1756100542053,
      "order": "normal"
    },
    {
      "name": "nuxt:remove-plugin-metadata",
      "start": 1756100542053,
      "end": 1756100542053,
      "order": "normal"
    },
    {
      "name": "nuxt:components:imports",
      "start": 1756100542053,
      "end": 1756100542053,
      "order": "normal"
    },
    {
      "name": "replace",
      "start": 1756100542053,
      "end": 1756100542053,
      "order": "normal"
    },
    {
      "name": "ssr-styles",
      "start": 1756100542053,
      "end": 1756100542053,
      "order": "normal"
    },
    {
      "name": "vite:define",
      "result": "import { resolveComponent as _resolveComponent } from \"vue\";\nimport { ssrRenderComponent as _ssrRenderComponent, ssrRenderStyle as _ssrRenderStyle, ssrRenderAttr as _ssrRenderAttr } from \"vue/server-renderer\";\nimport _imports_0 from \"@/assets/img/link.png\";\nimport _imports_1 from \"@/assets/img/tongxin1.png\";\nimport _imports_2 from \"@/assets/img/tongxin2.png\";\nimport _imports_3 from \"@/assets/img/tongxin3.png\";\nimport _imports_4 from \"@/assets/img/tongxin4.png\";\nimport _imports_5 from \"@/assets/img/tongxin5.png\";\nconst _sfc_main = {\n  __name: \"index\",\n  __ssrInlineRender: true,\n  setup(__props) {\n    const openWeb = () => {\n      (void 0).open(\"https://www.tongxin-xili.com.tw/\");\n    };\n    return (_ctx, _push, _parent, _attrs) => {\n      const _component_Navbar = _resolveComponent(\"Navbar\");\n      const _component_Footer = _resolveComponent(\"Footer\");\n      _push(`<!--[-->`);\n      _push(_ssrRenderComponent(_component_Navbar, null, null, _parent));\n      _push(`<div id=\"projectPage\" data-v-11a9daba><div class=\"container\" data-v-11a9daba><div class=\"title\" data-v-11a9daba>協力國際形象網站 <img style=\"${_ssrRenderStyle({ \"cursor\": \"pointer\" })}\"${_ssrRenderAttr(\"src\", _imports_0)} alt=\"\" data-v-11a9daba></div><div class=\"title-m\" data-v-11a9daba>協力國際管理顧問有限公司</div><div class=\"d-flex justify-content-center mt-3\" data-v-11a9daba><div class=\"main-img\" data-v-11a9daba><div class=\"main-border\" data-v-11a9daba><div class=\"second-border\" data-v-11a9daba><img${_ssrRenderAttr(\"src\", _imports_1)} alt=\"\" data-v-11a9daba></div></div></div></div><div class=\"background\" data-v-11a9daba><div class=\"title mt-5 mb-3\" data-v-11a9daba>專案背景</div><div class=\"content\" data-v-11a9daba>本專案旨在為協力國際管理顧問有限公司打造一個形象網站．</div></div><div class=\"skill\" data-v-11a9daba><div class=\"title\" data-v-11a9daba>技術應用</div><ul style=\"${_ssrRenderStyle({ \"margin-left\": \"2rem\", \"margin-top\": \"1rem\" })}\" data-v-11a9daba><li data-v-11a9daba>使用：html、css、JavaScript、Swiper、AOS、BootStrap</li></ul></div><div class=\"otherImg\" data-v-11a9daba><img${_ssrRenderAttr(\"src\", _imports_2)} alt=\"\" data-v-11a9daba></div><div class=\"otherImg\" data-v-11a9daba><img${_ssrRenderAttr(\"src\", _imports_3)} alt=\"\" data-v-11a9daba></div><div class=\"otherImg\" data-v-11a9daba><img${_ssrRenderAttr(\"src\", _imports_4)} alt=\"\" data-v-11a9daba></div><div class=\"otherImg\" data-v-11a9daba><img${_ssrRenderAttr(\"src\", _imports_5)} alt=\"\" data-v-11a9daba></div></div></div>`);\n      _push(_ssrRenderComponent(_component_Footer, null, null, _parent));\n      _push(`<!--]-->`);\n    };\n  }\n};\nimport \"/Users/yunhao/Project/website/pages/tongxin-xili-web/index.vue?vue&type=style&index=0&scoped=11a9daba&lang.css\";\nimport { useSSRContext as __vite_useSSRContext } from \"vue\";\nconst _sfc_setup = _sfc_main.setup;\n_sfc_main.setup = (props, ctx) => {\n  const ssrContext = __vite_useSSRContext();\n  (ssrContext.modules || (ssrContext.modules = /* @__PURE__ */ new Set())).add(\"pages/tongxin-xili-web/index.vue\");\n  return _sfc_setup ? _sfc_setup(props, ctx) : void 0;\n};\nimport _export_sfc from \"\\0plugin-vue:export-helper\";\nexport default /* @__PURE__ */ _export_sfc(_sfc_main, [[\"__scopeId\", \"data-v-11a9daba\"]]);\n",
      "start": 1756100542053,
      "end": 1756100544331,
      "order": "normal",
      "sourcemaps": "{\n  \"version\": 3,\n  \"sources\": [\"/Users/yunhao/Project/website/pages/tongxin-xili-web/index.vue\"],\n  \"sourcesContent\": [\"import { resolveComponent as _resolveComponent } from \\\"vue\\\"\\nimport { ssrRenderComponent as _ssrRenderComponent, ssrRenderStyle as _ssrRenderStyle, ssrRenderAttr as _ssrRenderAttr } from \\\"vue/server-renderer\\\"\\nimport _imports_0 from '@/assets/img/link.png'\\nimport _imports_1 from '@/assets/img/tongxin1.png'\\nimport _imports_2 from '@/assets/img/tongxin2.png'\\nimport _imports_3 from '@/assets/img/tongxin3.png'\\nimport _imports_4 from '@/assets/img/tongxin4.png'\\nimport _imports_5 from '@/assets/img/tongxin5.png'\\n\\n\\n\\nconst _sfc_main = {\\n  __name: 'index',\\n  __ssrInlineRender: true,\\n  setup(__props) {\\n\\nconst openWeb = () => {\\n  window.open(\\\"https://www.tongxin-xili.com.tw/\\\");\\n};\\n\\nreturn (_ctx, _push, _parent, _attrs) => {\\n  const _component_Navbar = _resolveComponent(\\\"Navbar\\\")\\n  const _component_Footer = _resolveComponent(\\\"Footer\\\")\\n\\n  _push(`<!--[-->`)\\n  _push(_ssrRenderComponent(_component_Navbar, null, null, _parent))\\n  _push(`<div id=\\\"projectPage\\\" data-v-11a9daba><div class=\\\"container\\\" data-v-11a9daba><div class=\\\"title\\\" data-v-11a9daba>協力國際形象網站 <img style=\\\"${\\n    _ssrRenderStyle({\\\"cursor\\\":\\\"pointer\\\"})\\n  }\\\"${\\n    _ssrRenderAttr(\\\"src\\\", _imports_0)\\n  } alt=\\\"\\\" data-v-11a9daba></div><div class=\\\"title-m\\\" data-v-11a9daba>協力國際管理顧問有限公司</div><div class=\\\"d-flex justify-content-center mt-3\\\" data-v-11a9daba><div class=\\\"main-img\\\" data-v-11a9daba><div class=\\\"main-border\\\" data-v-11a9daba><div class=\\\"second-border\\\" data-v-11a9daba><img${\\n    _ssrRenderAttr(\\\"src\\\", _imports_1)\\n  } alt=\\\"\\\" data-v-11a9daba></div></div></div></div><div class=\\\"background\\\" data-v-11a9daba><div class=\\\"title mt-5 mb-3\\\" data-v-11a9daba>專案背景</div><div class=\\\"content\\\" data-v-11a9daba>本專案旨在為協力國際管理顧問有限公司打造一個形象網站．</div></div><div class=\\\"skill\\\" data-v-11a9daba><div class=\\\"title\\\" data-v-11a9daba>技術應用</div><ul style=\\\"${\\n    _ssrRenderStyle({\\\"margin-left\\\":\\\"2rem\\\",\\\"margin-top\\\":\\\"1rem\\\"})\\n  }\\\" data-v-11a9daba><li data-v-11a9daba>使用：html、css、JavaScript、Swiper、AOS、BootStrap</li></ul></div><div class=\\\"otherImg\\\" data-v-11a9daba><img${\\n    _ssrRenderAttr(\\\"src\\\", _imports_2)\\n  } alt=\\\"\\\" data-v-11a9daba></div><div class=\\\"otherImg\\\" data-v-11a9daba><img${\\n    _ssrRenderAttr(\\\"src\\\", _imports_3)\\n  } alt=\\\"\\\" data-v-11a9daba></div><div class=\\\"otherImg\\\" data-v-11a9daba><img${\\n    _ssrRenderAttr(\\\"src\\\", _imports_4)\\n  } alt=\\\"\\\" data-v-11a9daba></div><div class=\\\"otherImg\\\" data-v-11a9daba><img${\\n    _ssrRenderAttr(\\\"src\\\", _imports_5)\\n  } alt=\\\"\\\" data-v-11a9daba></div></div></div>`)\\n  _push(_ssrRenderComponent(_component_Footer, null, null, _parent))\\n  _push(`<!--]-->`)\\n}\\n}\\n\\n}\\n\\n\\nimport \\\"/Users/yunhao/Project/website/pages/tongxin-xili-web/index.vue?vue&type=style&index=0&scoped=11a9daba&lang.css\\\"\\n\\nimport { useSSRContext as __vite_useSSRContext } from 'vue'\\nconst _sfc_setup = _sfc_main.setup\\n_sfc_main.setup = (props, ctx) => {\\n  const ssrContext = __vite_useSSRContext()\\n  ;(ssrContext.modules || (ssrContext.modules = new Set())).add(\\\"pages/tongxin-xili-web/index.vue\\\")\\n  return _sfc_setup ? _sfc_setup(props, ctx) : undefined\\n}\\nimport _export_sfc from '\\u0000plugin-vue:export-helper'\\nexport default /*#__PURE__*/_export_sfc(_sfc_main, [['__scopeId',\\\"data-v-11a9daba\\\"]])\"],\n  \"mappings\": \"AAAA,SAAS,oBAAoB,yBAAyB;AACtD,SAAS,sBAAsB,qBAAqB,kBAAkB,iBAAiB,iBAAiB,sBAAsB;AAC9H,OAAO,gBAAgB;AACvB,OAAO,gBAAgB;AACvB,OAAO,gBAAgB;AACvB,OAAO,gBAAgB;AACvB,OAAO,gBAAgB;AACvB,OAAO,gBAAgB;AAIvB,MAAM,YAAY;AAAA,EAChB,QAAQ;AAAA,EACR,mBAAmB;AAAA,EACnB,MAAM,SAAS;AAEjB,UAAM,UAAU,MAAM;AACpB,eAAO,KAAK,kCAAkC;AAAA,IAChD;AAEA,WAAO,CAAC,MAAM,OAAO,SAAS,WAAW;AACvC,YAAM,oBAAoB,kBAAkB,QAAQ;AACpD,YAAM,oBAAoB,kBAAkB,QAAQ;AAEpD,YAAM,UAAU;AAChB,YAAM,oBAAoB,mBAAmB,MAAM,MAAM,OAAO,CAAC;AACjE,YAAM,wIACJ,gBAAgB,EAAC,UAAS,UAAS,CAAC,CACtC,IACE,eAAe,OAAO,UAAU,CAClC,sRACE,eAAe,OAAO,UAAU,CAClC,yTACE,gBAAgB,EAAC,eAAc,QAAO,cAAa,OAAM,CAAC,CAC5D,8IACE,eAAe,OAAO,UAAU,CAClC,2EACE,eAAe,OAAO,UAAU,CAClC,2EACE,eAAe,OAAO,UAAU,CAClC,2EACE,eAAe,OAAO,UAAU,CAClC,4CAA4C;AAC5C,YAAM,oBAAoB,mBAAmB,MAAM,MAAM,OAAO,CAAC;AACjE,YAAM,UAAU;AAAA,IAClB;AAAA,EACA;AAEA;AAGA,OAAO;AAEP,SAAS,iBAAiB,4BAA4B;AACtD,MAAM,aAAa,UAAU;AAC7B,UAAU,QAAQ,CAAC,OAAO,QAAQ;AAChC,QAAM,aAAa,qBAAqB;AACvC,GAAC,WAAW,YAAY,WAAW,UAAU,oBAAI,IAAI,IAAI,IAAI,kCAAkC;AAChG,SAAO,aAAa,WAAW,OAAO,GAAG,IAAI;AAC/C;AACA,OAAO,iBAAiB;AACxB,eAA4B,4BAAY,WAAW,CAAC,CAAC,aAAY,iBAAiB,CAAC,CAAC;\",\n  \"names\": []\n}\n"
    },
    {
      "name": "vite:css-post",
      "start": 1756100544331,
      "end": 1756100544331,
      "order": "normal"
    },
    {
      "name": "vite:build-html",
      "start": 1756100544331,
      "end": 1756100544331,
      "order": "normal"
    },
    {
      "name": "vite:worker-import-meta-url",
      "start": 1756100544331,
      "end": 1756100544331,
      "order": "normal"
    },
    {
      "name": "vite:asset-import-meta-url",
      "start": 1756100544331,
      "end": 1756100544331,
      "order": "normal"
    },
    {
      "name": "commonjs",
      "start": 1756100544331,
      "end": 1756100544331,
      "order": "normal"
    },
    {
      "name": "vite:dynamic-import-vars",
      "start": 1756100544331,
      "end": 1756100544331,
      "order": "normal"
    },
    {
      "name": "vite:import-glob",
      "start": 1756100544331,
      "end": 1756100544331,
      "order": "normal"
    },
    {
      "name": "nuxt:composable-keys",
      "start": 1756100544331,
      "end": 1756100544331,
      "order": "post"
    },
    {
      "name": "nuxt:composable-keys",
      "start": 1756100544331,
      "end": 1756100544331,
      "order": "post"
    },
    {
      "name": "unplugin-vue-components",
      "result": "/* unplugin-vue-components disabled */import { resolveComponent as _resolveComponent } from \"vue\";\nimport { ssrRenderComponent as _ssrRenderComponent, ssrRenderStyle as _ssrRenderStyle, ssrRenderAttr as _ssrRenderAttr } from \"vue/server-renderer\";\nimport _imports_0 from \"@/assets/img/link.png\";\nimport _imports_1 from \"@/assets/img/tongxin1.png\";\nimport _imports_2 from \"@/assets/img/tongxin2.png\";\nimport _imports_3 from \"@/assets/img/tongxin3.png\";\nimport _imports_4 from \"@/assets/img/tongxin4.png\";\nimport _imports_5 from \"@/assets/img/tongxin5.png\";\nconst _sfc_main = {\n  __name: \"index\",\n  __ssrInlineRender: true,\n  setup(__props) {\n    const openWeb = () => {\n      (void 0).open(\"https://www.tongxin-xili.com.tw/\");\n    };\n    return (_ctx, _push, _parent, _attrs) => {\n      const _component_Navbar = _resolveComponent(\"Navbar\");\n      const _component_Footer = _resolveComponent(\"Footer\");\n      _push(`<!--[-->`);\n      _push(_ssrRenderComponent(_component_Navbar, null, null, _parent));\n      _push(`<div id=\"projectPage\" data-v-11a9daba><div class=\"container\" data-v-11a9daba><div class=\"title\" data-v-11a9daba>協力國際形象網站 <img style=\"${_ssrRenderStyle({ \"cursor\": \"pointer\" })}\"${_ssrRenderAttr(\"src\", _imports_0)} alt=\"\" data-v-11a9daba></div><div class=\"title-m\" data-v-11a9daba>協力國際管理顧問有限公司</div><div class=\"d-flex justify-content-center mt-3\" data-v-11a9daba><div class=\"main-img\" data-v-11a9daba><div class=\"main-border\" data-v-11a9daba><div class=\"second-border\" data-v-11a9daba><img${_ssrRenderAttr(\"src\", _imports_1)} alt=\"\" data-v-11a9daba></div></div></div></div><div class=\"background\" data-v-11a9daba><div class=\"title mt-5 mb-3\" data-v-11a9daba>專案背景</div><div class=\"content\" data-v-11a9daba>本專案旨在為協力國際管理顧問有限公司打造一個形象網站．</div></div><div class=\"skill\" data-v-11a9daba><div class=\"title\" data-v-11a9daba>技術應用</div><ul style=\"${_ssrRenderStyle({ \"margin-left\": \"2rem\", \"margin-top\": \"1rem\" })}\" data-v-11a9daba><li data-v-11a9daba>使用：html、css、JavaScript、Swiper、AOS、BootStrap</li></ul></div><div class=\"otherImg\" data-v-11a9daba><img${_ssrRenderAttr(\"src\", _imports_2)} alt=\"\" data-v-11a9daba></div><div class=\"otherImg\" data-v-11a9daba><img${_ssrRenderAttr(\"src\", _imports_3)} alt=\"\" data-v-11a9daba></div><div class=\"otherImg\" data-v-11a9daba><img${_ssrRenderAttr(\"src\", _imports_4)} alt=\"\" data-v-11a9daba></div><div class=\"otherImg\" data-v-11a9daba><img${_ssrRenderAttr(\"src\", _imports_5)} alt=\"\" data-v-11a9daba></div></div></div>`);\n      _push(_ssrRenderComponent(_component_Footer, null, null, _parent));\n      _push(`<!--]-->`);\n    };\n  }\n};\nimport \"/Users/yunhao/Project/website/pages/tongxin-xili-web/index.vue?vue&type=style&index=0&scoped=11a9daba&lang.css\";\nimport { useSSRContext as __vite_useSSRContext } from \"vue\";\nconst _sfc_setup = _sfc_main.setup;\n_sfc_main.setup = (props, ctx) => {\n  const ssrContext = __vite_useSSRContext();\n  (ssrContext.modules || (ssrContext.modules = /* @__PURE__ */ new Set())).add(\"pages/tongxin-xili-web/index.vue\");\n  return _sfc_setup ? _sfc_setup(props, ctx) : void 0;\n};\nimport _export_sfc from \"\\0plugin-vue:export-helper\";\nexport default /* @__PURE__ */ _export_sfc(_sfc_main, [[\"__scopeId\", \"data-v-11a9daba\"]]);\n",
      "start": 1756100544331,
      "end": 1756100544332,
      "order": "post",
      "sourcemaps": {
        "version": 3,
        "sources": [
          "/Users/yunhao/Project/website/pages/tongxin-xili-web/index.vue"
        ],
        "sourcesContent": [
          "import { resolveComponent as _resolveComponent } from \"vue\";\nimport { ssrRenderComponent as _ssrRenderComponent, ssrRenderStyle as _ssrRenderStyle, ssrRenderAttr as _ssrRenderAttr } from \"vue/server-renderer\";\nimport _imports_0 from \"@/assets/img/link.png\";\nimport _imports_1 from \"@/assets/img/tongxin1.png\";\nimport _imports_2 from \"@/assets/img/tongxin2.png\";\nimport _imports_3 from \"@/assets/img/tongxin3.png\";\nimport _imports_4 from \"@/assets/img/tongxin4.png\";\nimport _imports_5 from \"@/assets/img/tongxin5.png\";\nconst _sfc_main = {\n  __name: \"index\",\n  __ssrInlineRender: true,\n  setup(__props) {\n    const openWeb = () => {\n      (void 0).open(\"https://www.tongxin-xili.com.tw/\");\n    };\n    return (_ctx, _push, _parent, _attrs) => {\n      const _component_Navbar = _resolveComponent(\"Navbar\");\n      const _component_Footer = _resolveComponent(\"Footer\");\n      _push(`<!--[-->`);\n      _push(_ssrRenderComponent(_component_Navbar, null, null, _parent));\n      _push(`<div id=\"projectPage\" data-v-11a9daba><div class=\"container\" data-v-11a9daba><div class=\"title\" data-v-11a9daba>協力國際形象網站 <img style=\"${_ssrRenderStyle({ \"cursor\": \"pointer\" })}\"${_ssrRenderAttr(\"src\", _imports_0)} alt=\"\" data-v-11a9daba></div><div class=\"title-m\" data-v-11a9daba>協力國際管理顧問有限公司</div><div class=\"d-flex justify-content-center mt-3\" data-v-11a9daba><div class=\"main-img\" data-v-11a9daba><div class=\"main-border\" data-v-11a9daba><div class=\"second-border\" data-v-11a9daba><img${_ssrRenderAttr(\"src\", _imports_1)} alt=\"\" data-v-11a9daba></div></div></div></div><div class=\"background\" data-v-11a9daba><div class=\"title mt-5 mb-3\" data-v-11a9daba>專案背景</div><div class=\"content\" data-v-11a9daba>本專案旨在為協力國際管理顧問有限公司打造一個形象網站．</div></div><div class=\"skill\" data-v-11a9daba><div class=\"title\" data-v-11a9daba>技術應用</div><ul style=\"${_ssrRenderStyle({ \"margin-left\": \"2rem\", \"margin-top\": \"1rem\" })}\" data-v-11a9daba><li data-v-11a9daba>使用：html、css、JavaScript、Swiper、AOS、BootStrap</li></ul></div><div class=\"otherImg\" data-v-11a9daba><img${_ssrRenderAttr(\"src\", _imports_2)} alt=\"\" data-v-11a9daba></div><div class=\"otherImg\" data-v-11a9daba><img${_ssrRenderAttr(\"src\", _imports_3)} alt=\"\" data-v-11a9daba></div><div class=\"otherImg\" data-v-11a9daba><img${_ssrRenderAttr(\"src\", _imports_4)} alt=\"\" data-v-11a9daba></div><div class=\"otherImg\" data-v-11a9daba><img${_ssrRenderAttr(\"src\", _imports_5)} alt=\"\" data-v-11a9daba></div></div></div>`);\n      _push(_ssrRenderComponent(_component_Footer, null, null, _parent));\n      _push(`<!--]-->`);\n    };\n  }\n};\nimport \"/Users/yunhao/Project/website/pages/tongxin-xili-web/index.vue?vue&type=style&index=0&scoped=11a9daba&lang.css\";\nimport { useSSRContext as __vite_useSSRContext } from \"vue\";\nconst _sfc_setup = _sfc_main.setup;\n_sfc_main.setup = (props, ctx) => {\n  const ssrContext = __vite_useSSRContext();\n  (ssrContext.modules || (ssrContext.modules = /* @__PURE__ */ new Set())).add(\"pages/tongxin-xili-web/index.vue\");\n  return _sfc_setup ? _sfc_setup(props, ctx) : void 0;\n};\nimport _export_sfc from \"\\0plugin-vue:export-helper\";\nexport default /* @__PURE__ */ _export_sfc(_sfc_main, [[\"__scopeId\", \"data-v-11a9daba\"]]);\n"
        ],
        "names": [],
        "mappings": "sCAAA,MAAM,CAAC,CAAC,CAAC,gBAAgB,CAAC,EAAE,CAAC,iBAAiB,CAAC,CAAC,CAAC,IAAI,CAAC,CAAC,GAAG,CAAC,CAAC;AAC5D,MAAM,CAAC,CAAC,CAAC,kBAAkB,CAAC,EAAE,CAAC,mBAAmB,CAAC,CAAC,cAAc,CAAC,EAAE,CAAC,eAAe,CAAC,CAAC,aAAa,CAAC,EAAE,CAAC,cAAc,CAAC,CAAC,CAAC,IAAI,CAAC,CAAC,GAAG,CAAC,MAAM,CAAC,QAAQ,CAAC,CAAC;AACpJ,MAAM,CAAC,UAAU,CAAC,IAAI,CAAC,CAAC,CAAC,CAAC,MAAM,CAAC,GAAG,CAAC,IAAI,CAAC,GAAG,CAAC,CAAC;AAC/C,MAAM,CAAC,UAAU,CAAC,IAAI,CAAC,CAAC,CAAC,CAAC,MAAM,CAAC,GAAG,CAAC,QAAQ,CAAC,GAAG,CAAC,CAAC;AACnD,MAAM,CAAC,UAAU,CAAC,IAAI,CAAC,CAAC,CAAC,CAAC,MAAM,CAAC,GAAG,CAAC,QAAQ,CAAC,GAAG,CAAC,CAAC;AACnD,MAAM,CAAC,UAAU,CAAC,IAAI,CAAC,CAAC,CAAC,CAAC,MAAM,CAAC,GAAG,CAAC,QAAQ,CAAC,GAAG,CAAC,CAAC;AACnD,MAAM,CAAC,UAAU,CAAC,IAAI,CAAC,CAAC,CAAC,CAAC,MAAM,CAAC,GAAG,CAAC,QAAQ,CAAC,GAAG,CAAC,CAAC;AACnD,MAAM,CAAC,UAAU,CAAC,IAAI,CAAC,CAAC,CAAC,CAAC,MAAM,CAAC,GAAG,CAAC,QAAQ,CAAC,GAAG,CAAC,CAAC;AACnD,KAAK,CAAC,SAAS,CAAC,CAAC,CAAC,CAAC;AACnB,CAAC,CAAC,MAAM,CAAC,CAAC,CAAC,KAAK,CAAC,CAAC;AAClB,CAAC,CAAC,iBAAiB,CAAC,CAAC,IAAI,CAAC;AAC1B,CAAC,CAAC,KAAK,CAAC,OAAO,CAAC,CAAC,CAAC;AAClB,CAAC,CAAC,CAAC,CAAC,KAAK,CAAC,OAAO,CAAC,CAAC,CAAC,CAAC,CAAC,CAAC,CAAC,CAAC,CAAC,CAAC;AAC3B,CAAC,CAAC,CAAC,CAAC,CAAC,CAAC,CAAC,IAAI,CAAC,CAAC,CAAC,CAAC,IAAI,CAAC,CAAC,KAAK,CAAC,CAAC,CAAC,GAAG,CAAC,OAAO,CAAC,IAAI,CAAC,GAAG,CAAC,EAAE,CAAC,CAAC,CAAC,CAAC;AACxD,CAAC,CAAC,CAAC,CAAC,CAAC,CAAC;AACN,CAAC,CAAC,CAAC,CAAC,MAAM,CAAC,CAAC,IAAI,CAAC,CAAC,KAAK,CAAC,CAAC,OAAO,CAAC,CAAC,MAAM,CAAC,CAAC,CAAC,CAAC,CAAC,CAAC;AAC9C,CAAC,CAAC,CAAC,CAAC,CAAC,CAAC,KAAK,CAAC,iBAAiB,CAAC,CAAC,CAAC,iBAAiB,CAAC,CAAC,MAAM,CAAC,CAAC,CAAC;AAC5D,CAAC,CAAC,CAAC,CAAC,CAAC,CAAC,KAAK,CAAC,iBAAiB,CAAC,CAAC,CAAC,iBAAiB,CAAC,CAAC,MAAM,CAAC,CAAC,CAAC;AAC5D,CAAC,CAAC,CAAC,CAAC,CAAC,CAAC,KAAK,CAAC,CAAC,CAAC,CAAC,CAAC,CAAC,CAAC,CAAC,CAAC,CAAC,CAAC,CAAC,CAAC;AACxB,CAAC,CAAC,CAAC,CAAC,CAAC,CAAC,KAAK,CAAC,mBAAmB,CAAC,iBAAiB,CAAC,CAAC,IAAI,CAAC,CAAC,IAAI,CAAC,CAAC,OAAO,CAAC,CAAC,CAAC;AACzE,CAAC,CAAC,CAAC,CAAC,CAAC,CAAC,KAAK,CAAC,CAAC,CAAC,GAAG,CAAC,EAAE,CAAC,CAAC,WAAW,CAAC,CAAC,IAAI,CAAC,CAAC,CAAC,QAAQ,CAAC,CAAC,GAAG,CAAC,KAAK,CAAC,CAAC,SAAS,CAAC,CAAC,IAAI,CAAC,CAAC,CAAC,QAAQ,CAAC,CAAC,GAAG,CAAC,KAAK,CAAC,CAAC,KAAK,CAAC,CAAC,IAAI,CAAC,CAAC,CAAC,QAAQ,CAAC,CAAC,CAAC,CAAC,CAAC,CAAC,CAAC,CAAC,CAAC,CAAC,CAAC,GAAG,CAAC,KAAK,CAAC,CAAC,CAAC,CAAC,eAAe,CAAC,CAAC,CAAC,CAAC,MAAM,CAAC,CAAC,CAAC,CAAC,OAAO,CAAC,CAAC,CAAC,CAAC,CAAC,CAAC,CAAC,CAAC,cAAc,CAAC,CAAC,GAAG,CAAC,CAAC,CAAC,UAAU,CAAC,CAAC,CAAC,GAAG,CAAC,CAAC,CAAC,CAAC,IAAI,CAAC,CAAC,CAAC,QAAQ,CAAC,CAAC,CAAC,GAAG,CAAC,CAAC,GAAG,CAAC,KAAK,CAAC,CAAC,KAAK,CAAC,CAAC,CAAC,CAAC,IAAI,CAAC,CAAC,CAAC,QAAQ,CAAC,CAAC,CAAC,CAAC,CAAC,CAAC,CAAC,CAAC,CAAC,CAAC,CAAC,CAAC,CAAC,CAAC,CAAC,GAAG,CAAC,CAAC,GAAG,CAAC,KAAK,CAAC,CAAC,CAAC,CAAC,IAAI,CAAC,OAAO,CAAC,OAAO,CAAC,MAAM,CAAC,EAAE,CAAC,CAAC,CAAC,CAAC,IAAI,CAAC,CAAC,CAAC,QAAQ,CAAC,CAAC,GAAG,CAAC,KAAK,CAAC,CAAC,IAAI,CAAC,GAAG,CAAC,CAAC,IAAI,CAAC,CAAC,CAAC,QAAQ,CAAC,CAAC,GAAG,CAAC,KAAK,CAAC,CAAC,IAAI,CAAC,MAAM,CAAC,CAAC,IAAI,CAAC,CAAC,CAAC,QAAQ,CAAC,CAAC,GAAG,CAAC,KAAK,CAAC,CAAC,MAAM,CAAC,MAAM,CAAC,CAAC,IAAI,CAAC,CAAC,CAAC,QAAQ,CAAC,CAAC,GAAG,CAAC,CAAC,cAAc,CAAC,CAAC,GAAG,CAAC,CAAC,CAAC,UAAU,CAAC,CAAC,CAAC,GAAG,CAAC,CAAC,CAAC,CAAC,IAAI,CAAC,CAAC,CAAC,QAAQ,CAAC,CAAC,CAAC,GAAG,CAAC,CAAC,CAAC,GAAG,CAAC,CAAC,CAAC,GAAG,CAAC,CAAC,CAAC,GAAG,CAAC,CAAC,GAAG,CAAC,KAAK,CAAC,CAAC,UAAU,CAAC,CAAC,IAAI,CAAC,CAAC,CAAC,QAAQ,CAAC,CAAC,GAAG,CAAC,KAAK,CAAC,CAAC,KAAK,CAAC,EAAE,CAAC,CAAC,CAAC,EAAE,CAAC,CAAC,CAAC,CAAC,IAAI,CAAC,CAAC,CAAC,QAAQ,CAAC,CAAC,CAAC,CAAC,CAAC,CAAC,CAAC,GAAG,CAAC,CAAC,GAAG,CAAC,KAAK,CAAC,CAAC,OAAO,CAAC,CAAC,IAAI,CAAC,CAAC,CAAC,QAAQ,CAAC,CAAC,CAAC,CAAC,CAAC,CAAC,CAAC,CAAC,CAAC,CAAC,CAAC,CAAC,CAAC,CAAC,CAAC,CAAC,CAAC,CAAC,CAAC,CAAC,CAAC,CAAC,CAAC,CAAC,CAAC,CAAC,CAAC,CAAC,CAAC,CAAC,GAAG,CAAC,CAAC,CAAC,GAAG,CAAC,CAAC,GAAG,CAAC,KAAK,CAAC,CAAC,KAAK,CAAC,CAAC,IAAI,CAAC,CAAC,CAAC,QAAQ,CAAC,CAAC,GAAG,CAAC,KAAK,CAAC,CAAC,KAAK,CAAC,CAAC,IAAI,CAAC,CAAC,CAAC,QAAQ,CAAC,CAAC,CAAC,CAAC,CAAC,CAAC,CAAC,GAAG,CAAC,CAAC,EAAE,CAAC,KAAK,CAAC,CAAC,CAAC,CAAC,eAAe,CAAC,CAAC,CAAC,CAAC,MAAM,CAAC,IAAI,CAAC,CAAC,CAAC,CAAC,IAAI,CAAC,CAAC,CAAC,CAAC,MAAM,CAAC,GAAG,CAAC,CAAC,CAAC,CAAC,IAAI,CAAC,CAAC,CAAC,CAAC,CAAC,CAAC,CAAC,IAAI,CAAC,CAAC,CAAC,QAAQ,CAAC,CAAC,EAAE,CAAC,IAAI,CAAC,CAAC,CAAC,QAAQ,CAAC,CAAC,CAAC,CAAC,IAAI,CAAC,GAAG,CAAC,UAAU,CAAC,MAAM,CAAC,GAAG,CAAC,SAAS,CAAC,CAAC,EAAE,CAAC,CAAC,CAAC,EAAE,CAAC,CAAC,CAAC,GAAG,CAAC,CAAC,GAAG,CAAC,KAAK,CAAC,CAAC,QAAQ,CAAC,CAAC,IAAI,CAAC,CAAC,CAAC,QAAQ,CAAC,CAAC,GAAG,CAAC,CAAC,cAAc,CAAC,CAAC,GAAG,CAAC,CAAC,CAAC,UAAU,CAAC,CAAC,CAAC,GAAG,CAAC,CAAC,CAAC,CAAC,IAAI,CAAC,CAAC,CAAC,QAAQ,CAAC,CAAC,CAAC,GAAG,CAAC,CAAC,GAAG,CAAC,KAAK,CAAC,CAAC,QAAQ,CAAC,CAAC,IAAI,CAAC,CAAC,CAAC,QAAQ,CAAC,CAAC,GAAG,CAAC,CAAC,cAAc,CAAC,CAAC,GAAG,CAAC,CAAC,CAAC,UAAU,CAAC,CAAC,CAAC,GAAG,CAAC,CAAC,CAAC,CAAC,IAAI,CAAC,CAAC,CAAC,QAAQ,CAAC,CAAC,CAAC,GAAG,CAAC,CAAC,GAAG,CAAC,KAAK,CAAC,CAAC,QAAQ,CAAC,CAAC,IAAI,CAAC,CAAC,CAAC,QAAQ,CAAC,CAAC,GAAG,CAAC,CAAC,cAAc,CAAC,CAAC,GAAG,CAAC,CAAC,CAAC,UAAU,CAAC,CAAC,CAAC,GAAG,CAAC,CAAC,CAAC,CAAC,IAAI,CAAC,CAAC,CAAC,QAAQ,CAAC,CAAC,CAAC,GAAG,CAAC,CAAC,GAAG,CAAC,KAAK,CAAC,CAAC,QAAQ,CAAC,CAAC,IAAI,CAAC,CAAC,CAAC,QAAQ,CAAC,CAAC,GAAG,CAAC,CAAC,cAAc,CAAC,CAAC,GAAG,CAAC,CAAC,CAAC,UAAU,CAAC,CAAC,CAAC,GAAG,CAAC,CAAC,CAAC,CAAC,IAAI,CAAC,CAAC,CAAC,QAAQ,CAAC,CAAC,CAAC,GAAG,CAAC,CAAC,CAAC,GAAG,CAAC,CAAC,CAAC,GAAG,CAAC,CAAC,CAAC,CAAC;AACl7C,CAAC,CAAC,CAAC,CAAC,CAAC,CAAC,KAAK,CAAC,mBAAmB,CAAC,iBAAiB,CAAC,CAAC,IAAI,CAAC,CAAC,IAAI,CAAC,CAAC,OAAO,CAAC,CAAC,CAAC;AACzE,CAAC,CAAC,CAAC,CAAC,CAAC,CAAC,KAAK,CAAC,CAAC,CAAC,CAAC,CAAC,CAAC,CAAC,CAAC,CAAC,CAAC,CAAC,CAAC,CAAC;AACxB,CAAC,CAAC,CAAC,CAAC,CAAC,CAAC;AACN,CAAC,CAAC,CAAC;AACH,CAAC,CAAC;AACF,MAAM,CAAC,CAAC,CAAC,KAAK,CAAC,MAAM,CAAC,OAAO,CAAC,OAAO,CAAC,KAAK,CAAC,OAAO,CAAC,IAAI,CAAC,GAAG,CAAC,KAAK,CAAC,GAAG,CAAC,GAAG,CAAC,IAAI,CAAC,KAAK,CAAC,KAAK,CAAC,CAAC,CAAC,MAAM,CAAC,QAAQ,CAAC,IAAI,CAAC,GAAG,CAAC,CAAC;AACxH,MAAM,CAAC,CAAC,CAAC,aAAa,CAAC,EAAE,CAAC,oBAAoB,CAAC,CAAC,CAAC,IAAI,CAAC,CAAC,GAAG,CAAC,CAAC;AAC5D,KAAK,CAAC,UAAU,CAAC,CAAC,CAAC,SAAS,CAAC,KAAK,CAAC;AACnC,SAAS,CAAC,KAAK,CAAC,CAAC,CAAC,CAAC,KAAK,CAAC,CAAC,GAAG,CAAC,CAAC,CAAC,CAAC,CAAC,CAAC;AACnC,CAAC,CAAC,KAAK,CAAC,UAAU,CAAC,CAAC,CAAC,oBAAoB,CAAC,CAAC,CAAC;AAC5C,CAAC,CAAC,CAAC,UAAU,CAAC,OAAO,CAAC,CAAC,CAAC,CAAC,CAAC,UAAU,CAAC,OAAO,CAAC,CAAC,CAAC,CAAC,CAAC,CAAC,CAAC,QAAQ,CAAC,CAAC,CAAC,CAAC,GAAG,CAAC,GAAG,CAAC,CAAC,CAAC,CAAC,CAAC,GAAG,CAAC,CAAC,KAAK,CAAC,OAAO,CAAC,IAAI,CAAC,GAAG,CAAC,KAAK,CAAC,GAAG,CAAC,CAAC,CAAC;AACnH,CAAC,CAAC,MAAM,CAAC,UAAU,CAAC,CAAC,CAAC,UAAU,CAAC,KAAK,CAAC,CAAC,GAAG,CAAC,CAAC,CAAC,CAAC,IAAI,CAAC,CAAC,CAAC;AACtD,CAAC,CAAC;AACF,MAAM,CAAC,WAAW,CAAC,IAAI,CAAC,CAAC,CAAC,OAAO,CAAC,GAAG,CAAC,MAAM,CAAC,MAAM,CAAC,CAAC;AACrD,MAAM,CAAC,OAAO,CAAC,CAAC,CAAC,CAAC,CAAC,QAAQ,CAAC,CAAC,CAAC,CAAC,WAAW,CAAC,SAAS,CAAC,CAAC,CAAC,CAAC,CAAC,SAAS,CAAC,CAAC,CAAC,CAAC,IAAI,CAAC,CAAC,CAAC,QAAQ,CAAC,CAAC,CAAC,CAAC,CAAC;"
      }
    },
    {
      "name": "unplugin-vue-components",
      "result": "/* unplugin-vue-components disabled */import { resolveComponent as _resolveComponent } from \"vue\";\nimport { ssrRenderComponent as _ssrRenderComponent, ssrRenderStyle as _ssrRenderStyle, ssrRenderAttr as _ssrRenderAttr } from \"vue/server-renderer\";\nimport _imports_0 from \"@/assets/img/link.png\";\nimport _imports_1 from \"@/assets/img/tongxin1.png\";\nimport _imports_2 from \"@/assets/img/tongxin2.png\";\nimport _imports_3 from \"@/assets/img/tongxin3.png\";\nimport _imports_4 from \"@/assets/img/tongxin4.png\";\nimport _imports_5 from \"@/assets/img/tongxin5.png\";\nconst _sfc_main = {\n  __name: \"index\",\n  __ssrInlineRender: true,\n  setup(__props) {\n    const openWeb = () => {\n      (void 0).open(\"https://www.tongxin-xili.com.tw/\");\n    };\n    return (_ctx, _push, _parent, _attrs) => {\n      const _component_Navbar = _resolveComponent(\"Navbar\");\n      const _component_Footer = _resolveComponent(\"Footer\");\n      _push(`<!--[-->`);\n      _push(_ssrRenderComponent(_component_Navbar, null, null, _parent));\n      _push(`<div id=\"projectPage\" data-v-11a9daba><div class=\"container\" data-v-11a9daba><div class=\"title\" data-v-11a9daba>協力國際形象網站 <img style=\"${_ssrRenderStyle({ \"cursor\": \"pointer\" })}\"${_ssrRenderAttr(\"src\", _imports_0)} alt=\"\" data-v-11a9daba></div><div class=\"title-m\" data-v-11a9daba>協力國際管理顧問有限公司</div><div class=\"d-flex justify-content-center mt-3\" data-v-11a9daba><div class=\"main-img\" data-v-11a9daba><div class=\"main-border\" data-v-11a9daba><div class=\"second-border\" data-v-11a9daba><img${_ssrRenderAttr(\"src\", _imports_1)} alt=\"\" data-v-11a9daba></div></div></div></div><div class=\"background\" data-v-11a9daba><div class=\"title mt-5 mb-3\" data-v-11a9daba>專案背景</div><div class=\"content\" data-v-11a9daba>本專案旨在為協力國際管理顧問有限公司打造一個形象網站．</div></div><div class=\"skill\" data-v-11a9daba><div class=\"title\" data-v-11a9daba>技術應用</div><ul style=\"${_ssrRenderStyle({ \"margin-left\": \"2rem\", \"margin-top\": \"1rem\" })}\" data-v-11a9daba><li data-v-11a9daba>使用：html、css、JavaScript、Swiper、AOS、BootStrap</li></ul></div><div class=\"otherImg\" data-v-11a9daba><img${_ssrRenderAttr(\"src\", _imports_2)} alt=\"\" data-v-11a9daba></div><div class=\"otherImg\" data-v-11a9daba><img${_ssrRenderAttr(\"src\", _imports_3)} alt=\"\" data-v-11a9daba></div><div class=\"otherImg\" data-v-11a9daba><img${_ssrRenderAttr(\"src\", _imports_4)} alt=\"\" data-v-11a9daba></div><div class=\"otherImg\" data-v-11a9daba><img${_ssrRenderAttr(\"src\", _imports_5)} alt=\"\" data-v-11a9daba></div></div></div>`);\n      _push(_ssrRenderComponent(_component_Footer, null, null, _parent));\n      _push(`<!--]-->`);\n    };\n  }\n};\nimport \"/Users/yunhao/Project/website/pages/tongxin-xili-web/index.vue?vue&type=style&index=0&scoped=11a9daba&lang.css\";\nimport { useSSRContext as __vite_useSSRContext } from \"vue\";\nconst _sfc_setup = _sfc_main.setup;\n_sfc_main.setup = (props, ctx) => {\n  const ssrContext = __vite_useSSRContext();\n  (ssrContext.modules || (ssrContext.modules = /* @__PURE__ */ new Set())).add(\"pages/tongxin-xili-web/index.vue\");\n  return _sfc_setup ? _sfc_setup(props, ctx) : void 0;\n};\nimport _export_sfc from \"\\0plugin-vue:export-helper\";\nexport default /* @__PURE__ */ _export_sfc(_sfc_main, [[\"__scopeId\", \"data-v-11a9daba\"]]);\n",
      "start": 1756100544331,
      "end": 1756100544332,
      "order": "post",
      "sourcemaps": {
        "version": 3,
        "sources": [
          "/Users/yunhao/Project/website/pages/tongxin-xili-web/index.vue"
        ],
        "sourcesContent": [
          "import { resolveComponent as _resolveComponent } from \"vue\";\nimport { ssrRenderComponent as _ssrRenderComponent, ssrRenderStyle as _ssrRenderStyle, ssrRenderAttr as _ssrRenderAttr } from \"vue/server-renderer\";\nimport _imports_0 from \"@/assets/img/link.png\";\nimport _imports_1 from \"@/assets/img/tongxin1.png\";\nimport _imports_2 from \"@/assets/img/tongxin2.png\";\nimport _imports_3 from \"@/assets/img/tongxin3.png\";\nimport _imports_4 from \"@/assets/img/tongxin4.png\";\nimport _imports_5 from \"@/assets/img/tongxin5.png\";\nconst _sfc_main = {\n  __name: \"index\",\n  __ssrInlineRender: true,\n  setup(__props) {\n    const openWeb = () => {\n      (void 0).open(\"https://www.tongxin-xili.com.tw/\");\n    };\n    return (_ctx, _push, _parent, _attrs) => {\n      const _component_Navbar = _resolveComponent(\"Navbar\");\n      const _component_Footer = _resolveComponent(\"Footer\");\n      _push(`<!--[-->`);\n      _push(_ssrRenderComponent(_component_Navbar, null, null, _parent));\n      _push(`<div id=\"projectPage\" data-v-11a9daba><div class=\"container\" data-v-11a9daba><div class=\"title\" data-v-11a9daba>協力國際形象網站 <img style=\"${_ssrRenderStyle({ \"cursor\": \"pointer\" })}\"${_ssrRenderAttr(\"src\", _imports_0)} alt=\"\" data-v-11a9daba></div><div class=\"title-m\" data-v-11a9daba>協力國際管理顧問有限公司</div><div class=\"d-flex justify-content-center mt-3\" data-v-11a9daba><div class=\"main-img\" data-v-11a9daba><div class=\"main-border\" data-v-11a9daba><div class=\"second-border\" data-v-11a9daba><img${_ssrRenderAttr(\"src\", _imports_1)} alt=\"\" data-v-11a9daba></div></div></div></div><div class=\"background\" data-v-11a9daba><div class=\"title mt-5 mb-3\" data-v-11a9daba>專案背景</div><div class=\"content\" data-v-11a9daba>本專案旨在為協力國際管理顧問有限公司打造一個形象網站．</div></div><div class=\"skill\" data-v-11a9daba><div class=\"title\" data-v-11a9daba>技術應用</div><ul style=\"${_ssrRenderStyle({ \"margin-left\": \"2rem\", \"margin-top\": \"1rem\" })}\" data-v-11a9daba><li data-v-11a9daba>使用：html、css、JavaScript、Swiper、AOS、BootStrap</li></ul></div><div class=\"otherImg\" data-v-11a9daba><img${_ssrRenderAttr(\"src\", _imports_2)} alt=\"\" data-v-11a9daba></div><div class=\"otherImg\" data-v-11a9daba><img${_ssrRenderAttr(\"src\", _imports_3)} alt=\"\" data-v-11a9daba></div><div class=\"otherImg\" data-v-11a9daba><img${_ssrRenderAttr(\"src\", _imports_4)} alt=\"\" data-v-11a9daba></div><div class=\"otherImg\" data-v-11a9daba><img${_ssrRenderAttr(\"src\", _imports_5)} alt=\"\" data-v-11a9daba></div></div></div>`);\n      _push(_ssrRenderComponent(_component_Footer, null, null, _parent));\n      _push(`<!--]-->`);\n    };\n  }\n};\nimport \"/Users/yunhao/Project/website/pages/tongxin-xili-web/index.vue?vue&type=style&index=0&scoped=11a9daba&lang.css\";\nimport { useSSRContext as __vite_useSSRContext } from \"vue\";\nconst _sfc_setup = _sfc_main.setup;\n_sfc_main.setup = (props, ctx) => {\n  const ssrContext = __vite_useSSRContext();\n  (ssrContext.modules || (ssrContext.modules = /* @__PURE__ */ new Set())).add(\"pages/tongxin-xili-web/index.vue\");\n  return _sfc_setup ? _sfc_setup(props, ctx) : void 0;\n};\nimport _export_sfc from \"\\0plugin-vue:export-helper\";\nexport default /* @__PURE__ */ _export_sfc(_sfc_main, [[\"__scopeId\", \"data-v-11a9daba\"]]);\n"
        ],
        "names": [],
        "mappings": "sCAAA,MAAM,CAAC,CAAC,CAAC,gBAAgB,CAAC,EAAE,CAAC,iBAAiB,CAAC,CAAC,CAAC,IAAI,CAAC,CAAC,GAAG,CAAC,CAAC;AAC5D,MAAM,CAAC,CAAC,CAAC,kBAAkB,CAAC,EAAE,CAAC,mBAAmB,CAAC,CAAC,cAAc,CAAC,EAAE,CAAC,eAAe,CAAC,CAAC,aAAa,CAAC,EAAE,CAAC,cAAc,CAAC,CAAC,CAAC,IAAI,CAAC,CAAC,GAAG,CAAC,MAAM,CAAC,QAAQ,CAAC,CAAC;AACpJ,MAAM,CAAC,UAAU,CAAC,IAAI,CAAC,CAAC,CAAC,CAAC,MAAM,CAAC,GAAG,CAAC,IAAI,CAAC,GAAG,CAAC,CAAC;AAC/C,MAAM,CAAC,UAAU,CAAC,IAAI,CAAC,CAAC,CAAC,CAAC,MAAM,CAAC,GAAG,CAAC,QAAQ,CAAC,GAAG,CAAC,CAAC;AACnD,MAAM,CAAC,UAAU,CAAC,IAAI,CAAC,CAAC,CAAC,CAAC,MAAM,CAAC,GAAG,CAAC,QAAQ,CAAC,GAAG,CAAC,CAAC;AACnD,MAAM,CAAC,UAAU,CAAC,IAAI,CAAC,CAAC,CAAC,CAAC,MAAM,CAAC,GAAG,CAAC,QAAQ,CAAC,GAAG,CAAC,CAAC;AACnD,MAAM,CAAC,UAAU,CAAC,IAAI,CAAC,CAAC,CAAC,CAAC,MAAM,CAAC,GAAG,CAAC,QAAQ,CAAC,GAAG,CAAC,CAAC;AACnD,MAAM,CAAC,UAAU,CAAC,IAAI,CAAC,CAAC,CAAC,CAAC,MAAM,CAAC,GAAG,CAAC,QAAQ,CAAC,GAAG,CAAC,CAAC;AACnD,KAAK,CAAC,SAAS,CAAC,CAAC,CAAC,CAAC;AACnB,CAAC,CAAC,MAAM,CAAC,CAAC,CAAC,KAAK,CAAC,CAAC;AAClB,CAAC,CAAC,iBAAiB,CAAC,CAAC,IAAI,CAAC;AAC1B,CAAC,CAAC,KAAK,CAAC,OAAO,CAAC,CAAC,CAAC;AAClB,CAAC,CAAC,CAAC,CAAC,KAAK,CAAC,OAAO,CAAC,CAAC,CAAC,CAAC,CAAC,CAAC,CAAC,CAAC,CAAC,CAAC;AAC3B,CAAC,CAAC,CAAC,CAAC,CAAC,CAAC,CAAC,IAAI,CAAC,CAAC,CAAC,CAAC,IAAI,CAAC,CAAC,KAAK,CAAC,CAAC,CAAC,GAAG,CAAC,OAAO,CAAC,IAAI,CAAC,GAAG,CAAC,EAAE,CAAC,CAAC,CAAC,CAAC;AACxD,CAAC,CAAC,CAAC,CAAC,CAAC,CAAC;AACN,CAAC,CAAC,CAAC,CAAC,MAAM,CAAC,CAAC,IAAI,CAAC,CAAC,KAAK,CAAC,CAAC,OAAO,CAAC,CAAC,MAAM,CAAC,CAAC,CAAC,CAAC,CAAC,CAAC;AAC9C,CAAC,CAAC,CAAC,CAAC,CAAC,CAAC,KAAK,CAAC,iBAAiB,CAAC,CAAC,CAAC,iBAAiB,CAAC,CAAC,MAAM,CAAC,CAAC,CAAC;AAC5D,CAAC,CAAC,CAAC,CAAC,CAAC,CAAC,KAAK,CAAC,iBAAiB,CAAC,CAAC,CAAC,iBAAiB,CAAC,CAAC,MAAM,CAAC,CAAC,CAAC;AAC5D,CAAC,CAAC,CAAC,CAAC,CAAC,CAAC,KAAK,CAAC,CAAC,CAAC,CAAC,CAAC,CAAC,CAAC,CAAC,CAAC,CAAC,CAAC,CAAC,CAAC;AACxB,CAAC,CAAC,CAAC,CAAC,CAAC,CAAC,KAAK,CAAC,mBAAmB,CAAC,iBAAiB,CAAC,CAAC,IAAI,CAAC,CAAC,IAAI,CAAC,CAAC,OAAO,CAAC,CAAC,CAAC;AACzE,CAAC,CAAC,CAAC,CAAC,CAAC,CAAC,KAAK,CAAC,CAAC,CAAC,GAAG,CAAC,EAAE,CAAC,CAAC,WAAW,CAAC,CAAC,IAAI,CAAC,CAAC,CAAC,QAAQ,CAAC,CAAC,GAAG,CAAC,KAAK,CAAC,CAAC,SAAS,CAAC,CAAC,IAAI,CAAC,CAAC,CAAC,QAAQ,CAAC,CAAC,GAAG,CAAC,KAAK,CAAC,CAAC,KAAK,CAAC,CAAC,IAAI,CAAC,CAAC,CAAC,QAAQ,CAAC,CAAC,CAAC,CAAC,CAAC,CAAC,CAAC,CAAC,CAAC,CAAC,CAAC,GAAG,CAAC,KAAK,CAAC,CAAC,CAAC,CAAC,eAAe,CAAC,CAAC,CAAC,CAAC,MAAM,CAAC,CAAC,CAAC,CAAC,OAAO,CAAC,CAAC,CAAC,CAAC,CAAC,CAAC,CAAC,CAAC,cAAc,CAAC,CAAC,GAAG,CAAC,CAAC,CAAC,UAAU,CAAC,CAAC,CAAC,GAAG,CAAC,CAAC,CAAC,CAAC,IAAI,CAAC,CAAC,CAAC,QAAQ,CAAC,CAAC,CAAC,GAAG,CAAC,CAAC,GAAG,CAAC,KAAK,CAAC,CAAC,KAAK,CAAC,CAAC,CAAC,CAAC,IAAI,CAAC,CAAC,CAAC,QAAQ,CAAC,CAAC,CAAC,CAAC,CAAC,CAAC,CAAC,CAAC,CAAC,CAAC,CAAC,CAAC,CAAC,CAAC,CAAC,GAAG,CAAC,CAAC,GAAG,CAAC,KAAK,CAAC,CAAC,CAAC,CAAC,IAAI,CAAC,OAAO,CAAC,OAAO,CAAC,MAAM,CAAC,EAAE,CAAC,CAAC,CAAC,CAAC,IAAI,CAAC,CAAC,CAAC,QAAQ,CAAC,CAAC,GAAG,CAAC,KAAK,CAAC,CAAC,IAAI,CAAC,GAAG,CAAC,CAAC,IAAI,CAAC,CAAC,CAAC,QAAQ,CAAC,CAAC,GAAG,CAAC,KAAK,CAAC,CAAC,IAAI,CAAC,MAAM,CAAC,CAAC,IAAI,CAAC,CAAC,CAAC,QAAQ,CAAC,CAAC,GAAG,CAAC,KAAK,CAAC,CAAC,MAAM,CAAC,MAAM,CAAC,CAAC,IAAI,CAAC,CAAC,CAAC,QAAQ,CAAC,CAAC,GAAG,CAAC,CAAC,cAAc,CAAC,CAAC,GAAG,CAAC,CAAC,CAAC,UAAU,CAAC,CAAC,CAAC,GAAG,CAAC,CAAC,CAAC,CAAC,IAAI,CAAC,CAAC,CAAC,QAAQ,CAAC,CAAC,CAAC,GAAG,CAAC,CAAC,CAAC,GAAG,CAAC,CAAC,CAAC,GAAG,CAAC,CAAC,CAAC,GAAG,CAAC,CAAC,GAAG,CAAC,KAAK,CAAC,CAAC,UAAU,CAAC,CAAC,IAAI,CAAC,CAAC,CAAC,QAAQ,CAAC,CAAC,GAAG,CAAC,KAAK,CAAC,CAAC,KAAK,CAAC,EAAE,CAAC,CAAC,CAAC,EAAE,CAAC,CAAC,CAAC,CAAC,IAAI,CAAC,CAAC,CAAC,QAAQ,CAAC,CAAC,CAAC,CAAC,CAAC,CAAC,CAAC,GAAG,CAAC,CAAC,GAAG,CAAC,KAAK,CAAC,CAAC,OAAO,CAAC,CAAC,IAAI,CAAC,CAAC,CAAC,QAAQ,CAAC,CAAC,CAAC,CAAC,CAAC,CAAC,CAAC,CAAC,CAAC,CAAC,CAAC,CAAC,CAAC,CAAC,CAAC,CAAC,CAAC,CAAC,CAAC,CAAC,CAAC,CAAC,CAAC,CAAC,CAAC,CAAC,CAAC,CAAC,CAAC,CAAC,GAAG,CAAC,CAAC,CAAC,GAAG,CAAC,CAAC,GAAG,CAAC,KAAK,CAAC,CAAC,KAAK,CAAC,CAAC,IAAI,CAAC,CAAC,CAAC,QAAQ,CAAC,CAAC,GAAG,CAAC,KAAK,CAAC,CAAC,KAAK,CAAC,CAAC,IAAI,CAAC,CAAC,CAAC,QAAQ,CAAC,CAAC,CAAC,CAAC,CAAC,CAAC,CAAC,GAAG,CAAC,CAAC,EAAE,CAAC,KAAK,CAAC,CAAC,CAAC,CAAC,eAAe,CAAC,CAAC,CAAC,CAAC,MAAM,CAAC,IAAI,CAAC,CAAC,CAAC,CAAC,IAAI,CAAC,CAAC,CAAC,CAAC,MAAM,CAAC,GAAG,CAAC,CAAC,CAAC,CAAC,IAAI,CAAC,CAAC,CAAC,CAAC,CAAC,CAAC,CAAC,IAAI,CAAC,CAAC,CAAC,QAAQ,CAAC,CAAC,EAAE,CAAC,IAAI,CAAC,CAAC,CAAC,QAAQ,CAAC,CAAC,CAAC,CAAC,IAAI,CAAC,GAAG,CAAC,UAAU,CAAC,MAAM,CAAC,GAAG,CAAC,SAAS,CAAC,CAAC,EAAE,CAAC,CAAC,CAAC,EAAE,CAAC,CAAC,CAAC,GAAG,CAAC,CAAC,GAAG,CAAC,KAAK,CAAC,CAAC,QAAQ,CAAC,CAAC,IAAI,CAAC,CAAC,CAAC,QAAQ,CAAC,CAAC,GAAG,CAAC,CAAC,cAAc,CAAC,CAAC,GAAG,CAAC,CAAC,CAAC,UAAU,CAAC,CAAC,CAAC,GAAG,CAAC,CAAC,CAAC,CAAC,IAAI,CAAC,CAAC,CAAC,QAAQ,CAAC,CAAC,CAAC,GAAG,CAAC,CAAC,GAAG,CAAC,KAAK,CAAC,CAAC,QAAQ,CAAC,CAAC,IAAI,CAAC,CAAC,CAAC,QAAQ,CAAC,CAAC,GAAG,CAAC,CAAC,cAAc,CAAC,CAAC,GAAG,CAAC,CAAC,CAAC,UAAU,CAAC,CAAC,CAAC,GAAG,CAAC,CAAC,CAAC,CAAC,IAAI,CAAC,CAAC,CAAC,QAAQ,CAAC,CAAC,CAAC,GAAG,CAAC,CAAC,GAAG,CAAC,KAAK,CAAC,CAAC,QAAQ,CAAC,CAAC,IAAI,CAAC,CAAC,CAAC,QAAQ,CAAC,CAAC,GAAG,CAAC,CAAC,cAAc,CAAC,CAAC,GAAG,CAAC,CAAC,CAAC,UAAU,CAAC,CAAC,CAAC,GAAG,CAAC,CAAC,CAAC,CAAC,IAAI,CAAC,CAAC,CAAC,QAAQ,CAAC,CAAC,CAAC,GAAG,CAAC,CAAC,GAAG,CAAC,KAAK,CAAC,CAAC,QAAQ,CAAC,CAAC,IAAI,CAAC,CAAC,CAAC,QAAQ,CAAC,CAAC,GAAG,CAAC,CAAC,cAAc,CAAC,CAAC,GAAG,CAAC,CAAC,CAAC,UAAU,CAAC,CAAC,CAAC,GAAG,CAAC,CAAC,CAAC,CAAC,IAAI,CAAC,CAAC,CAAC,QAAQ,CAAC,CAAC,CAAC,GAAG,CAAC,CAAC,CAAC,GAAG,CAAC,CAAC,CAAC,GAAG,CAAC,CAAC,CAAC,CAAC;AACl7C,CAAC,CAAC,CAAC,CAAC,CAAC,CAAC,KAAK,CAAC,mBAAmB,CAAC,iBAAiB,CAAC,CAAC,IAAI,CAAC,CAAC,IAAI,CAAC,CAAC,OAAO,CAAC,CAAC,CAAC;AACzE,CAAC,CAAC,CAAC,CAAC,CAAC,CAAC,KAAK,CAAC,CAAC,CAAC,CAAC,CAAC,CAAC,CAAC,CAAC,CAAC,CAAC,CAAC,CAAC,CAAC;AACxB,CAAC,CAAC,CAAC,CAAC,CAAC,CAAC;AACN,CAAC,CAAC,CAAC;AACH,CAAC,CAAC;AACF,MAAM,CAAC,CAAC,CAAC,KAAK,CAAC,MAAM,CAAC,OAAO,CAAC,OAAO,CAAC,KAAK,CAAC,OAAO,CAAC,IAAI,CAAC,GAAG,CAAC,KAAK,CAAC,GAAG,CAAC,GAAG,CAAC,IAAI,CAAC,KAAK,CAAC,KAAK,CAAC,CAAC,CAAC,MAAM,CAAC,QAAQ,CAAC,IAAI,CAAC,GAAG,CAAC,CAAC;AACxH,MAAM,CAAC,CAAC,CAAC,aAAa,CAAC,EAAE,CAAC,oBAAoB,CAAC,CAAC,CAAC,IAAI,CAAC,CAAC,GAAG,CAAC,CAAC;AAC5D,KAAK,CAAC,UAAU,CAAC,CAAC,CAAC,SAAS,CAAC,KAAK,CAAC;AACnC,SAAS,CAAC,KAAK,CAAC,CAAC,CAAC,CAAC,KAAK,CAAC,CAAC,GAAG,CAAC,CAAC,CAAC,CAAC,CAAC,CAAC;AACnC,CAAC,CAAC,KAAK,CAAC,UAAU,CAAC,CAAC,CAAC,oBAAoB,CAAC,CAAC,CAAC;AAC5C,CAAC,CAAC,CAAC,UAAU,CAAC,OAAO,CAAC,CAAC,CAAC,CAAC,CAAC,UAAU,CAAC,OAAO,CAAC,CAAC,CAAC,CAAC,CAAC,CAAC,CAAC,QAAQ,CAAC,CAAC,CAAC,CAAC,GAAG,CAAC,GAAG,CAAC,CAAC,CAAC,CAAC,CAAC,GAAG,CAAC,CAAC,KAAK,CAAC,OAAO,CAAC,IAAI,CAAC,GAAG,CAAC,KAAK,CAAC,GAAG,CAAC,CAAC,CAAC;AACnH,CAAC,CAAC,MAAM,CAAC,UAAU,CAAC,CAAC,CAAC,UAAU,CAAC,KAAK,CAAC,CAAC,GAAG,CAAC,CAAC,CAAC,CAAC,IAAI,CAAC,CAAC,CAAC;AACtD,CAAC,CAAC;AACF,MAAM,CAAC,WAAW,CAAC,IAAI,CAAC,CAAC,CAAC,OAAO,CAAC,GAAG,CAAC,MAAM,CAAC,MAAM,CAAC,CAAC;AACrD,MAAM,CAAC,OAAO,CAAC,CAAC,CAAC,CAAC,CAAC,QAAQ,CAAC,CAAC,CAAC,CAAC,WAAW,CAAC,SAAS,CAAC,CAAC,CAAC,CAAC,CAAC,SAAS,CAAC,CAAC,CAAC,CAAC,IAAI,CAAC,CAAC,CAAC,QAAQ,CAAC,CAAC,CAAC,CAAC,CAAC;"
      }
    },
    {
      "name": "nuxt:imports-transform",
      "start": 1756100544332,
      "end": 1756100544332,
      "order": "post"
    },
    {
      "name": "nuxt:imports-transform",
      "start": 1756100544332,
      "end": 1756100544332,
      "order": "post"
    },
    {
      "name": "unctx:transform",
      "start": 1756100544332,
      "end": 1756100544332,
      "order": "post"
    },
    {
      "name": "unctx:transform",
      "start": 1756100544332,
      "end": 1756100544332,
      "order": "post"
    },
    {
      "name": "nuxt:pages-macros-transform",
      "start": 1756100544332,
      "end": 1756100544332,
      "order": "post"
    },
    {
      "name": "nuxt:pages-macros-transform",
      "start": 1756100544332,
      "end": 1756100544332,
      "order": "post"
    },
    {
      "name": "element-plus:transform",
      "start": 1756100544332,
      "end": 1756100544332,
      "order": "post"
    },
    {
      "name": "vant:transform",
      "start": 1756100544332,
      "end": 1756100544332,
      "order": "post"
    },
    {
      "name": "nuxt:tree-shake-template",
      "start": 1756100544332,
      "end": 1756100544332,
      "order": "post"
    },
    {
      "name": "nuxt:components-loader",
      "result": "import { default as __nuxt_component_0 } from \"/Users/yunhao/Project/website/components/Navbar.vue\";\nimport { default as __nuxt_component_1 } from \"/Users/yunhao/Project/website/components/Footer.vue\";\n/* unplugin-vue-components disabled */import { resolveComponent as _resolveComponent } from \"vue\";\nimport { ssrRenderComponent as _ssrRenderComponent, ssrRenderStyle as _ssrRenderStyle, ssrRenderAttr as _ssrRenderAttr } from \"vue/server-renderer\";\nimport _imports_0 from \"@/assets/img/link.png\";\nimport _imports_1 from \"@/assets/img/tongxin1.png\";\nimport _imports_2 from \"@/assets/img/tongxin2.png\";\nimport _imports_3 from \"@/assets/img/tongxin3.png\";\nimport _imports_4 from \"@/assets/img/tongxin4.png\";\nimport _imports_5 from \"@/assets/img/tongxin5.png\";\nconst _sfc_main = {\n  __name: \"index\",\n  __ssrInlineRender: true,\n  setup(__props) {\n    const openWeb = () => {\n      (void 0).open(\"https://www.tongxin-xili.com.tw/\");\n    };\n    return (_ctx, _push, _parent, _attrs) => {\n      const _component_Navbar = __nuxt_component_0;\n      const _component_Footer = __nuxt_component_1;\n      _push(`<!--[-->`);\n      _push(_ssrRenderComponent(_component_Navbar, null, null, _parent));\n      _push(`<div id=\"projectPage\" data-v-11a9daba><div class=\"container\" data-v-11a9daba><div class=\"title\" data-v-11a9daba>協力國際形象網站 <img style=\"${_ssrRenderStyle({ \"cursor\": \"pointer\" })}\"${_ssrRenderAttr(\"src\", _imports_0)} alt=\"\" data-v-11a9daba></div><div class=\"title-m\" data-v-11a9daba>協力國際管理顧問有限公司</div><div class=\"d-flex justify-content-center mt-3\" data-v-11a9daba><div class=\"main-img\" data-v-11a9daba><div class=\"main-border\" data-v-11a9daba><div class=\"second-border\" data-v-11a9daba><img${_ssrRenderAttr(\"src\", _imports_1)} alt=\"\" data-v-11a9daba></div></div></div></div><div class=\"background\" data-v-11a9daba><div class=\"title mt-5 mb-3\" data-v-11a9daba>專案背景</div><div class=\"content\" data-v-11a9daba>本專案旨在為協力國際管理顧問有限公司打造一個形象網站．</div></div><div class=\"skill\" data-v-11a9daba><div class=\"title\" data-v-11a9daba>技術應用</div><ul style=\"${_ssrRenderStyle({ \"margin-left\": \"2rem\", \"margin-top\": \"1rem\" })}\" data-v-11a9daba><li data-v-11a9daba>使用：html、css、JavaScript、Swiper、AOS、BootStrap</li></ul></div><div class=\"otherImg\" data-v-11a9daba><img${_ssrRenderAttr(\"src\", _imports_2)} alt=\"\" data-v-11a9daba></div><div class=\"otherImg\" data-v-11a9daba><img${_ssrRenderAttr(\"src\", _imports_3)} alt=\"\" data-v-11a9daba></div><div class=\"otherImg\" data-v-11a9daba><img${_ssrRenderAttr(\"src\", _imports_4)} alt=\"\" data-v-11a9daba></div><div class=\"otherImg\" data-v-11a9daba><img${_ssrRenderAttr(\"src\", _imports_5)} alt=\"\" data-v-11a9daba></div></div></div>`);\n      _push(_ssrRenderComponent(_component_Footer, null, null, _parent));\n      _push(`<!--]-->`);\n    };\n  }\n};\nimport \"/Users/yunhao/Project/website/pages/tongxin-xili-web/index.vue?vue&type=style&index=0&scoped=11a9daba&lang.css\";\nimport { useSSRContext as __vite_useSSRContext } from \"vue\";\nconst _sfc_setup = _sfc_main.setup;\n_sfc_main.setup = (props, ctx) => {\n  const ssrContext = __vite_useSSRContext();\n  (ssrContext.modules || (ssrContext.modules = /* @__PURE__ */ new Set())).add(\"pages/tongxin-xili-web/index.vue\");\n  return _sfc_setup ? _sfc_setup(props, ctx) : void 0;\n};\nimport _export_sfc from \"\\0plugin-vue:export-helper\";\nexport default /* @__PURE__ */ _export_sfc(_sfc_main, [[\"__scopeId\", \"data-v-11a9daba\"]]);\n",
      "start": 1756100544332,
      "end": 1756100544333,
      "order": "post",
      "sourcemaps": {
        "version": 3,
        "sources": [
          ""
        ],
        "names": [],
        "mappings": ";;AAAA,CAAC,CAAC,CAAC,CAAC,CAAC,CAAC,CAAC,CAAC,CAAC,CAAC,CAAC,CAAC,CAAC,CAAC,CAAC,CAAC,CAAC,CAAC,CAAC,CAAC,CAAC,CAAC,CAAC,CAAC,CAAC,CAAC,CAAC,CAAC,CAAC,CAAC,CAAC,CAAC,CAAC,CAAC,CAAC,CAAC,CAAC,CAAC,CAAC,CAAC,CAAC,CAAC,CAAC,CAAC,CAAC,CAAC,CAAC,CAAC,CAAC,CAAC,CAAC,CAAC,CAAC,CAAC,CAAC,CAAC,CAAC,CAAC,CAAC,CAAC,CAAC,CAAC,CAAC,CAAC,CAAC,CAAC,CAAC,CAAC,CAAC,CAAC,CAAC,CAAC,CAAC,CAAC,CAAC,CAAC,CAAC,CAAC,CAAC,CAAC,CAAC,CAAC,CAAC,CAAC,CAAC,CAAC,CAAC,CAAC,CAAC,CAAC,CAAC,CAAC,CAAC,CAAC,CAAC,CAAC,CAAC,CAAC;AAClG,CAAC,CAAC,CAAC,CAAC,CAAC,CAAC,CAAC,CAAC,CAAC,CAAC,CAAC,CAAC,CAAC,CAAC,CAAC,CAAC,CAAC,CAAC,CAAC,CAAC,CAAC,CAAC,CAAC,CAAC,CAAC,CAAC,CAAC,CAAC,CAAC,CAAC,CAAC,CAAC,CAAC,CAAC,CAAC,CAAC,CAAC,CAAC,CAAC,CAAC,CAAC,CAAC,CAAC,CAAC,CAAC,CAAC,CAAC,CAAC,CAAC,CAAC,CAAC,CAAC,CAAC,CAAC,CAAC,CAAC,CAAC,CAAC,CAAC,CAAC,CAAC,CAAC,CAAC,CAAC,CAAC,CAAC,CAAC,CAAC,CAAC,CAAC,CAAC,CAAC,CAAC,CAAC,CAAC,CAAC,CAAC,CAAC,CAAC,CAAC,CAAC,CAAC,CAAC,CAAC,CAAC,CAAC,CAAC,CAAC,CAAC,CAAC,CAAC,CAAC,CAAC,CAAC,CAAC,CAAC,CAAC,CAAC,CAAC,CAAC,CAAC,CAAC,CAAC,CAAC,CAAC,CAAC,CAAC,CAAC,CAAC,CAAC,CAAC,CAAC,CAAC,CAAC,CAAC,CAAC,CAAC,CAAC,CAAC,CAAC,CAAC,CAAC,CAAC,CAAC,CAAC,CAAC,CAAC,CAAC,CAAC,CAAC,CAAC,CAAC,CAAC,CAAC,CAAC,CAAC,CAAC,CAAC,CAAC,CAAC,CAAC,CAAC,CAAC,CAAC,CAAC,CAAC,CAAC,CAAC;AACpJ,CAAC,CAAC,CAAC,CAAC,CAAC,CAAC,CAAC,CAAC,CAAC,CAAC,CAAC,CAAC,CAAC,CAAC,CAAC,CAAC,CAAC,CAAC,CAAC,CAAC,CAAC,CAAC,CAAC,CAAC,CAAC,CAAC,CAAC,CAAC,CAAC,CAAC,CAAC,CAAC,CAAC,CAAC,CAAC,CAAC,CAAC,CAAC,CAAC,CAAC,CAAC,CAAC,CAAC,CAAC,CAAC,CAAC,CAAC;AAC/C,CAAC,CAAC,CAAC,CAAC,CAAC,CAAC,CAAC,CAAC,CAAC,CAAC,CAAC,CAAC,CAAC,CAAC,CAAC,CAAC,CAAC,CAAC,CAAC,CAAC,CAAC,CAAC,CAAC,CAAC,CAAC,CAAC,CAAC,CAAC,CAAC,CAAC,CAAC,CAAC,CAAC,CAAC,CAAC,CAAC,CAAC,CAAC,CAAC,CAAC,CAAC,CAAC,CAAC,CAAC,CAAC,CAAC,CAAC,CAAC,CAAC,CAAC,CAAC;AACnD,CAAC,CAAC,CAAC,CAAC,CAAC,CAAC,CAAC,CAAC,CAAC,CAAC,CAAC,CAAC,CAAC,CAAC,CAAC,CAAC,CAAC,CAAC,CAAC,CAAC,CAAC,CAAC,CAAC,CAAC,CAAC,CAAC,CAAC,CAAC,CAAC,CAAC,CAAC,CAAC,CAAC,CAAC,CAAC,CAAC,CAAC,CAAC,CAAC,CAAC,CAAC,CAAC,CAAC,CAAC,CAAC,CAAC,CAAC,CAAC,CAAC,CAAC,CAAC;AACnD,CAAC,CAAC,CAAC,CAAC,CAAC,CAAC,CAAC,CAAC,CAAC,CAAC,CAAC,CAAC,CAAC,CAAC,CAAC,CAAC,CAAC,CAAC,CAAC,CAAC,CAAC,CAAC,CAAC,CAAC,CAAC,CAAC,CAAC,CAAC,CAAC,CAAC,CAAC,CAAC,CAAC,CAAC,CAAC,CAAC,CAAC,CAAC,CAAC,CAAC,CAAC,CAAC,CAAC,CAAC,CAAC,CAAC,CAAC,CAAC,CAAC,CAAC,CAAC;AACnD,CAAC,CAAC,CAAC,CAAC,CAAC,CAAC,CAAC,CAAC,CAAC,CAAC,CAAC,CAAC,CAAC,CAAC,CAAC,CAAC,CAAC,CAAC,CAAC,CAAC,CAAC,CAAC,CAAC,CAAC,CAAC,CAAC,CAAC,CAAC,CAAC,CAAC,CAAC,CAAC,CAAC,CAAC,CAAC,CAAC,CAAC,CAAC,CAAC,CAAC,CAAC,CAAC,CAAC,CAAC,CAAC,CAAC,CAAC,CAAC,CAAC,CAAC,CAAC;AACnD,CAAC,CAAC,CAAC,CAAC,CAAC,CAAC,CAAC,CAAC,CAAC,CAAC,CAAC,CAAC,CAAC,CAAC,CAAC,CAAC,CAAC,CAAC,CAAC,CAAC,CAAC,CAAC,CAAC,CAAC,CAAC,CAAC,CAAC,CAAC,CAAC,CAAC,CAAC,CAAC,CAAC,CAAC,CAAC,CAAC,CAAC,CAAC,CAAC,CAAC,CAAC,CAAC,CAAC,CAAC,CAAC,CAAC,CAAC,CAAC,CAAC,CAAC,CAAC;AACnD,CAAC,CAAC,CAAC,CAAC,CAAC,CAAC,CAAC,CAAC,CAAC,CAAC,CAAC,CAAC,CAAC,CAAC,CAAC,CAAC,CAAC,CAAC,CAAC;AACnB,CAAC,CAAC,CAAC,CAAC,CAAC,CAAC,CAAC,CAAC,CAAC,CAAC,CAAC,CAAC,CAAC,CAAC,CAAC,CAAC,CAAC,CAAC;AAClB,CAAC,CAAC,CAAC,CAAC,CAAC,CAAC,CAAC,CAAC,CAAC,CAAC,CAAC,CAAC,CAAC,CAAC,CAAC,CAAC,CAAC,CAAC,CAAC,CAAC,CAAC,CAAC,CAAC,CAAC,CAAC,CAAC;AAC1B,CAAC,CAAC,CAAC,CAAC,CAAC,CAAC,CAAC,CAAC,CAAC,CAAC,CAAC,CAAC,CAAC,CAAC,CAAC,CAAC,CAAC,CAAC;AAClB,CAAC,CAAC,CAAC,CAAC,CAAC,CAAC,CAAC,CAAC,CAAC,CAAC,CAAC,CAAC,CAAC,CAAC,CAAC,CAAC,CAAC,CAAC,CAAC,CAAC,CAAC,CAAC,CAAC,CAAC,CAAC,CAAC,CAAC;AAC3B,CAAC,CAAC,CAAC,CAAC,CAAC,CAAC,CAAC,CAAC,CAAC,CAAC,CAAC,CAAC,CAAC,CAAC,CAAC,CAAC,CAAC,CAAC,CAAC,CAAC,CAAC,CAAC,CAAC,CAAC,CAAC,CAAC,CAAC,CAAC,CAAC,CAAC,CAAC,CAAC,CAAC,CAAC,CAAC,CAAC,CAAC,CAAC,CAAC,CAAC,CAAC,CAAC,CAAC,CAAC,CAAC,CAAC,CAAC,CAAC,CAAC,CAAC,CAAC,CAAC,CAAC,CAAC,CAAC,CAAC;AACxD,CAAC,CAAC,CAAC,CAAC,CAAC,CAAC;AACN,CAAC,CAAC,CAAC,CAAC,CAAC,CAAC,CAAC,CAAC,CAAC,CAAC,CAAC,CAAC,CAAC,CAAC,CAAC,CAAC,CAAC,CAAC,CAAC,CAAC,CAAC,CAAC,CAAC,CAAC,CAAC,CAAC,CAAC,CAAC,CAAC,CAAC,CAAC,CAAC,CAAC,CAAC,CAAC,CAAC,CAAC,CAAC,CAAC,CAAC,CAAC,CAAC,CAAC,CAAC,CAAC,CAAC;AAC9C,CAAC,CAAC,CAAC,CAAC,CAAC,CAAC,CAAC,CAAC,CAAC,CAAC,CAAC,CAAC,CAAC,CAAC,CAAC,CAAC,CAAC,CAAC,CAAC,CAAC,CAAC,CAAC,CAAC,CAAC,CAAC,CAAC,CAAC,CAAC,CAAC,CAAC,CAAC,CAAC,kBAA2B,CAAC;AAC5D,CAAC,CAAC,CAAC,CAAC,CAAC,CAAC,CAAC,CAAC,CAAC,CAAC,CAAC,CAAC,CAAC,CAAC,CAAC,CAAC,CAAC,CAAC,CAAC,CAAC,CAAC,CAAC,CAAC,CAAC,CAAC,CAAC,CAAC,CAAC,CAAC,CAAC,CAAC,CAAC,kBAA2B,CAAC;AAC5D,CAAC,CAAC,CAAC,CAAC,CAAC,CAAC,CAAC,CAAC,CAAC,CAAC,CAAC,CAAC,CAAC,CAAC,CAAC,CAAC,CAAC,CAAC,CAAC,CAAC,CAAC,CAAC,CAAC,CAAC;AACxB,CAAC,CAAC,CAAC,CAAC,CAAC,CAAC,CAAC,CAAC,CAAC,CAAC,CAAC,CAAC,CAAC,CAAC,CAAC,CAAC,CAAC,CAAC,CAAC,CAAC,CAAC,CAAC,CAAC,CAAC,CAAC,CAAC,CAAC,CAAC,CAAC,CAAC,CAAC,CAAC,CAAC,CAAC,CAAC,CAAC,CAAC,CAAC,CAAC,CAAC,CAAC,CAAC,CAAC,CAAC,CAAC,CAAC,CAAC,CAAC,CAAC,CAAC,CAAC,CAAC,CAAC,CAAC,CAAC,CAAC,CAAC,CAAC,CAAC,CAAC,CAAC,CAAC,CAAC,CAAC,CAAC,CAAC,CAAC,CAAC,CAAC,CAAC,CAAC,CAAC,CAAC;AACzE,CAAC,CAAC,CAAC,CAAC,CAAC,CAAC,CAAC,CAAC,CAAC,CAAC,CAAC,CAAC,CAAC,CAAC,CAAC,CAAC,CAAC,CAAC,CAAC,CAAC,CAAC,CAAC,CAAC,CAAC,CAAC,CAAC,CAAC,CAAC,CAAC,CAAC,CAAC,CAAC,CAAC,CAAC,CAAC,CAAC,CAAC,CAAC,CAAC,CAAC,CAAC,CAAC,CAAC,CAAC,CAAC,CAAC,CAAC,CAAC,CAAC,CAAC,CAAC,CAAC,CAAC,CAAC,CAAC,CAAC,CAAC,CAAC,CAAC,CAAC,CAAC,CAAC,CAAC,CAAC,CAAC,CAAC,CAAC,CAAC,CAAC,CAAC,CAAC,CAAC,CAAC,CAAC,CAAC,CAAC,CAAC,CAAC,CAAC,CAAC,CAAC,CAAC,CAAC,CAAC,CAAC,CAAC,CAAC,CAAC,CAAC,CAAC,CAAC,CAAC,CAAC,CAAC,CAAC,CAAC,CAAC,CAAC,CAAC,CAAC,CAAC,CAAC,CAAC,CAAC,CAAC,CAAC,CAAC,CAAC,CAAC,CAAC,CAAC,CAAC,CAAC,CAAC,CAAC,CAAC,CAAC,CAAC,CAAC,CAAC,CAAC,CAAC,CAAC,CAAC,CAAC,CAAC,CAAC,CAAC,CAAC,CAAC,CAAC,CAAC,CAAC,CAAC,CAAC,CAAC,CAAC,CAAC,CAAC,CAAC,CAAC,CAAC,CAAC,CAAC,CAAC,CAAC,CAAC,CAAC,CAAC,CAAC,CAAC,CAAC,CAAC,CAAC,CAAC,CAAC,CAAC,CAAC,CAAC,CAAC,CAAC,CAAC,CAAC,CAAC,CAAC,CAAC,CAAC,CAAC,CAAC,CAAC,CAAC,CAAC,CAAC,CAAC,CAAC,CAAC,CAAC,CAAC,CAAC,CAAC,CAAC,CAAC,CAAC,CAAC,CAAC,CAAC,CAAC,CAAC,CAAC,CAAC,CAAC,CAAC,CAAC,CAAC,CAAC,CAAC,CAAC,CAAC,CAAC,CAAC,CAAC,CAAC,CAAC,CAAC,CAAC,CAAC,CAAC,CAAC,CAAC,CAAC,CAAC,CAAC,CAAC,CAAC,CAAC,CAAC,CAAC,CAAC,CAAC,CAAC,CAAC,CAAC,CAAC,CAAC,CAAC,CAAC,CAAC,CAAC,CAAC,CAAC,CAAC,CAAC,CAAC,CAAC,CAAC,CAAC,CAAC,CAAC,CAAC,CAAC,CAAC,CAAC,CAAC,CAAC,CAAC,CAAC,CAAC,CAAC,CAAC,CAAC,CAAC,CAAC,CAAC,CAAC,CAAC,CAAC,CAAC,CAAC,CAAC,CAAC,CAAC,CAAC,CAAC,CAAC,CAAC,CAAC,CAAC,CAAC,CAAC,CAAC,CAAC,CAAC,CAAC,CAAC,CAAC,CAAC,CAAC,CAAC,CAAC,CAAC,CAAC,CAAC,CAAC,CAAC,CAAC,CAAC,CAAC,CAAC,CAAC,CAAC,CAAC,CAAC,CAAC,CAAC,CAAC,CAAC,CAAC,CAAC,CAAC,CAAC,CAAC,CAAC,CAAC,CAAC,CAAC,CAAC,CAAC,CAAC,CAAC,CAAC,CAAC,CAAC,CAAC,CAAC,CAAC,CAAC,CAAC,CAAC,CAAC,CAAC,CAAC,CAAC,CAAC,CAAC,CAAC,CAAC,CAAC,CAAC,CAAC,CAAC,CAAC,CAAC,CAAC,CAAC,CAAC,CAAC,CAAC,CAAC,CAAC,CAAC,CAAC,CAAC,CAAC,CAAC,CAAC,CAAC,CAAC,CAAC,CAAC,CAAC,CAAC,CAAC,CAAC,CAAC,CAAC,CAAC,CAAC,CAAC,CAAC,CAAC,CAAC,CAAC,CAAC,CAAC,CAAC,CAAC,CAAC,CAAC,CAAC,CAAC,CAAC,CAAC,CAAC,CAAC,CAAC,CAAC,CAAC,CAAC,CAAC,CAAC,CAAC,CAAC,CAAC,CAAC,CAAC,CAAC,CAAC,CAAC,CAAC,CAAC,CAAC,CAAC,CAAC,CAAC,CAAC,CAAC,CAAC,CAAC,CAAC,CAAC,CAAC,CAAC,CAAC,CAAC,CAAC,CAAC,CAAC,CAAC,CAAC,CAAC,CAAC,CAAC,CAAC,CAAC,CAAC,CAAC,CAAC,CAAC,CAAC,CAAC,CAAC,CAAC,CAAC,CAAC,CAAC,CAAC,CAAC,CAAC,CAAC,CAAC,CAAC,CAAC,CAAC,CAAC,CAAC,CAAC,CAAC,CAAC,CAAC,CAAC,CAAC,CAAC,CAAC,CAAC,CAAC,CAAC,CAAC,CAAC,CAAC,CAAC,CAAC,CAAC,CAAC,CAAC,CAAC,CAAC,CAAC,CAAC,CAAC,CAAC,CAAC,CAAC,CAAC,CAAC,CAAC,CAAC,CAAC,CAAC,CAAC,CAAC,CAAC,CAAC,CAAC,CAAC,CAAC,CAAC,CAAC,CAAC,CAAC,CAAC,CAAC,CAAC,CAAC,CAAC,CAAC,CAAC,CAAC,CAAC,CAAC,CAAC,CAAC,CAAC,CAAC,CAAC,CAAC,CAAC,CAAC,CAAC,CAAC,CAAC,CAAC,CAAC,CAAC,CAAC,CAAC,CAAC,CAAC,CAAC,CAAC,CAAC,CAAC,CAAC,CAAC,CAAC,CAAC,CAAC,CAAC,CAAC,CAAC,CAAC,CAAC,CAAC,CAAC,CAAC,CAAC,CAAC,CAAC,CAAC,CAAC,CAAC,CAAC,CAAC,CAAC,CAAC,CAAC,CAAC,CAAC,CAAC,CAAC,CAAC,CAAC,CAAC,CAAC,CAAC,CAAC,CAAC,CAAC,CAAC,CAAC,CAAC,CAAC,CAAC,CAAC,CAAC,CAAC,CAAC,CAAC,CAAC,CAAC,CAAC,CAAC,CAAC,CAAC,CAAC,CAAC,CAAC,CAAC,CAAC,CAAC,CAAC,CAAC,CAAC,CAAC,CAAC,CAAC,CAAC,CAAC,CAAC,CAAC,CAAC,CAAC,CAAC,CAAC,CAAC,CAAC,CAAC,CAAC,CAAC,CAAC,CAAC,CAAC,CAAC,CAAC,CAAC,CAAC,CAAC,CAAC,CAAC,CAAC,CAAC,CAAC,CAAC,CAAC,CAAC,CAAC,CAAC,CAAC,CAAC,CAAC,CAAC,CAAC,CAAC,CAAC,CAAC,CAAC,CAAC,CAAC,CAAC,CAAC,CAAC,CAAC,CAAC,CAAC,CAAC,CAAC,CAAC,CAAC,CAAC,CAAC,CAAC,CAAC,CAAC,CAAC,CAAC,CAAC,CAAC,CAAC,CAAC,CAAC,CAAC,CAAC,CAAC,CAAC,CAAC,CAAC,CAAC,CAAC,CAAC,CAAC,CAAC,CAAC,CAAC,CAAC,CAAC,CAAC,CAAC,CAAC,CAAC,CAAC,CAAC,CAAC,CAAC,CAAC,CAAC,CAAC,CAAC,CAAC,CAAC,CAAC,CAAC,CAAC,CAAC,CAAC,CAAC,CAAC,CAAC,CAAC,CAAC,CAAC,CAAC,CAAC,CAAC,CAAC,CAAC,CAAC,CAAC,CAAC,CAAC,CAAC,CAAC,CAAC,CAAC,CAAC,CAAC,CAAC,CAAC,CAAC,CAAC,CAAC,CAAC,CAAC,CAAC,CAAC,CAAC,CAAC,CAAC,CAAC,CAAC,CAAC,CAAC,CAAC,CAAC,CAAC,CAAC,CAAC,CAAC,CAAC,CAAC,CAAC,CAAC,CAAC,CAAC,CAAC,CAAC,CAAC,CAAC,CAAC,CAAC,CAAC,CAAC,CAAC,CAAC,CAAC,CAAC,CAAC,CAAC,CAAC,CAAC,CAAC,CAAC,CAAC,CAAC,CAAC,CAAC,CAAC,CAAC,CAAC,CAAC,CAAC,CAAC,CAAC,CAAC,CAAC,CAAC,CAAC,CAAC,CAAC,CAAC,CAAC,CAAC,CAAC,CAAC,CAAC,CAAC,CAAC,CAAC,CAAC,CAAC,CAAC,CAAC,CAAC,CAAC,CAAC,CAAC,CAAC,CAAC,CAAC,CAAC,CAAC,CAAC,CAAC,CAAC,CAAC,CAAC,CAAC,CAAC,CAAC,CAAC,CAAC,CAAC,CAAC,CAAC,CAAC,CAAC,CAAC,CAAC,CAAC,CAAC,CAAC,CAAC,CAAC,CAAC,CAAC,CAAC,CAAC,CAAC,CAAC,CAAC,CAAC,CAAC,CAAC,CAAC,CAAC,CAAC,CAAC,CAAC,CAAC,CAAC,CAAC,CAAC,CAAC,CAAC,CAAC,CAAC,CAAC,CAAC,CAAC,CAAC,CAAC,CAAC,CAAC,CAAC,CAAC,CAAC,CAAC,CAAC,CAAC,CAAC,CAAC,CAAC,CAAC,CAAC,CAAC,CAAC,CAAC,CAAC,CAAC,CAAC,CAAC,CAAC,CAAC,CAAC,CAAC,CAAC,CAAC,CAAC,CAAC,CAAC,CAAC,CAAC,CAAC,CAAC,CAAC,CAAC,CAAC,CAAC,CAAC,CAAC,CAAC,CAAC,CAAC,CAAC,CAAC,CAAC,CAAC,CAAC,CAAC,CAAC,CAAC,CAAC,CAAC,CAAC,CAAC,CAAC,CAAC,CAAC,CAAC,CAAC,CAAC,CAAC,CAAC,CAAC,CAAC,CAAC,CAAC,CAAC,CAAC,CAAC,CAAC,CAAC,CAAC,CAAC,CAAC,CAAC,CAAC,CAAC,CAAC,CAAC,CAAC,CAAC,CAAC,CAAC,CAAC,CAAC,CAAC,CAAC,CAAC,CAAC,CAAC,CAAC,CAAC,CAAC,CAAC,CAAC,CAAC,CAAC,CAAC,CAAC,CAAC,CAAC,CAAC,CAAC,CAAC,CAAC,CAAC,CAAC,CAAC,CAAC,CAAC,CAAC,CAAC,CAAC,CAAC,CAAC,CAAC,CAAC,CAAC,CAAC,CAAC,CAAC,CAAC,CAAC,CAAC,CAAC,CAAC,CAAC,CAAC,CAAC,CAAC,CAAC,CAAC,CAAC,CAAC,CAAC,CAAC,CAAC,CAAC,CAAC,CAAC,CAAC,CAAC,CAAC,CAAC,CAAC,CAAC,CAAC,CAAC,CAAC,CAAC,CAAC,CAAC,CAAC,CAAC,CAAC,CAAC,CAAC,CAAC,CAAC,CAAC,CAAC,CAAC,CAAC,CAAC,CAAC,CAAC,CAAC,CAAC,CAAC,CAAC,CAAC,CAAC,CAAC,CAAC,CAAC,CAAC,CAAC,CAAC,CAAC,CAAC,CAAC,CAAC,CAAC,CAAC,CAAC,CAAC,CAAC,CAAC,CAAC,CAAC,CAAC,CAAC,CAAC,CAAC,CAAC,CAAC,CAAC,CAAC,CAAC,CAAC,CAAC,CAAC,CAAC,CAAC,CAAC,CAAC,CAAC,CAAC,CAAC,CAAC,CAAC,CAAC,CAAC,CAAC,CAAC,CAAC,CAAC,CAAC,CAAC,CAAC,CAAC,CAAC,CAAC,CAAC,CAAC,CAAC,CAAC,CAAC,CAAC,CAAC,CAAC,CAAC,CAAC,CAAC,CAAC,CAAC,CAAC,CAAC,CAAC,CAAC,CAAC,CAAC,CAAC,CAAC,CAAC,CAAC,CAAC,CAAC,CAAC,CAAC,CAAC,CAAC,CAAC,CAAC,CAAC,CAAC,CAAC,CAAC,CAAC,CAAC,CAAC,CAAC,CAAC,CAAC,CAAC,CAAC,CAAC,CAAC,CAAC,CAAC,CAAC,CAAC,CAAC,CAAC,CAAC,CAAC,CAAC,CAAC,CAAC,CAAC,CAAC,CAAC,CAAC,CAAC,CAAC,CAAC,CAAC,CAAC,CAAC,CAAC,CAAC,CAAC,CAAC,CAAC,CAAC,CAAC,CAAC,CAAC,CAAC,CAAC,CAAC,CAAC,CAAC,CAAC,CAAC,CAAC,CAAC,CAAC,CAAC,CAAC,CAAC,CAAC,CAAC,CAAC,CAAC,CAAC,CAAC,CAAC,CAAC,CAAC,CAAC,CAAC,CAAC,CAAC,CAAC,CAAC,CAAC,CAAC,CAAC,CAAC,CAAC,CAAC,CAAC,CAAC,CAAC,CAAC,CAAC,CAAC,CAAC,CAAC,CAAC,CAAC,CAAC,CAAC,CAAC,CAAC,CAAC,CAAC,CAAC,CAAC,CAAC,CAAC,CAAC,CAAC,CAAC,CAAC,CAAC,CAAC,CAAC,CAAC,CAAC,CAAC,CAAC,CAAC,CAAC,CAAC,CAAC,CAAC,CAAC,CAAC,CAAC,CAAC,CAAC,CAAC,CAAC,CAAC,CAAC,CAAC,CAAC,CAAC,CAAC,CAAC,CAAC,CAAC,CAAC,CAAC,CAAC,CAAC,CAAC,CAAC,CAAC,CAAC,CAAC,CAAC,CAAC,CAAC,CAAC,CAAC,CAAC,CAAC,CAAC,CAAC,CAAC,CAAC,CAAC,CAAC,CAAC,CAAC,CAAC,CAAC,CAAC,CAAC,CAAC,CAAC,CAAC,CAAC,CAAC,CAAC,CAAC,CAAC,CAAC,CAAC,CAAC,CAAC,CAAC,CAAC,CAAC,CAAC,CAAC,CAAC,CAAC,CAAC,CAAC,CAAC,CAAC,CAAC,CAAC,CAAC,CAAC,CAAC,CAAC,CAAC,CAAC,CAAC,CAAC,CAAC,CAAC,CAAC,CAAC,CAAC,CAAC,CAAC,CAAC,CAAC,CAAC,CAAC,CAAC,CAAC,CAAC,CAAC,CAAC,CAAC,CAAC,CAAC,CAAC,CAAC,CAAC,CAAC,CAAC,CAAC,CAAC,CAAC,CAAC,CAAC,CAAC,CAAC,CAAC,CAAC,CAAC,CAAC,CAAC,CAAC,CAAC,CAAC,CAAC,CAAC,CAAC,CAAC,CAAC,CAAC,CAAC,CAAC,CAAC,CAAC,CAAC,CAAC,CAAC,CAAC,CAAC,CAAC,CAAC,CAAC,CAAC,CAAC,CAAC,CAAC,CAAC,CAAC,CAAC,CAAC,CAAC,CAAC,CAAC,CAAC,CAAC,CAAC,CAAC,CAAC,CAAC,CAAC,CAAC,CAAC,CAAC,CAAC,CAAC,CAAC,CAAC,CAAC,CAAC,CAAC,CAAC,CAAC,CAAC,CAAC,CAAC,CAAC,CAAC,CAAC,CAAC,CAAC,CAAC,CAAC,CAAC,CAAC,CAAC,CAAC,CAAC,CAAC,CAAC,CAAC,CAAC,CAAC,CAAC,CAAC,CAAC,CAAC,CAAC,CAAC,CAAC,CAAC,CAAC,CAAC,CAAC,CAAC,CAAC,CAAC,CAAC,CAAC,CAAC,CAAC,CAAC,CAAC,CAAC,CAAC,CAAC,CAAC,CAAC,CAAC,CAAC,CAAC,CAAC,CAAC,CAAC,CAAC,CAAC,CAAC,CAAC,CAAC,CAAC,CAAC,CAAC,CAAC,CAAC,CAAC,CAAC,CAAC,CAAC,CAAC,CAAC,CAAC,CAAC,CAAC,CAAC,CAAC,CAAC,CAAC,CAAC,CAAC,CAAC,CAAC,CAAC,CAAC,CAAC,CAAC,CAAC,CAAC,CAAC,CAAC,CAAC,CAAC,CAAC,CAAC,CAAC,CAAC,CAAC,CAAC,CAAC,CAAC,CAAC;AACl7C,CAAC,CAAC,CAAC,CAAC,CAAC,CAAC,CAAC,CAAC,CAAC,CAAC,CAAC,CAAC,CAAC,CAAC,CAAC,CAAC,CAAC,CAAC,CAAC,CAAC,CAAC,CAAC,CAAC,CAAC,CAAC,CAAC,CAAC,CAAC,CAAC,CAAC,CAAC,CAAC,CAAC,CAAC,CAAC,CAAC,CAAC,CAAC,CAAC,CAAC,CAAC,CAAC,CAAC,CAAC,CAAC,CAAC,CAAC,CAAC,CAAC,CAAC,CAAC,CAAC,CAAC,CAAC,CAAC,CAAC,CAAC,CAAC,CAAC,CAAC,CAAC,CAAC,CAAC,CAAC,CAAC,CAAC,CAAC,CAAC,CAAC,CAAC,CAAC,CAAC,CAAC;AACzE,CAAC,CAAC,CAAC,CAAC,CAAC,CAAC,CAAC,CAAC,CAAC,CAAC,CAAC,CAAC,CAAC,CAAC,CAAC,CAAC,CAAC,CAAC,CAAC,CAAC,CAAC,CAAC,CAAC,CAAC;AACxB,CAAC,CAAC,CAAC,CAAC,CAAC,CAAC;AACN,CAAC,CAAC,CAAC;AACH,CAAC,CAAC;AACF,CAAC,CAAC,CAAC,CAAC,CAAC,CAAC,CAAC,CAAC,CAAC,CAAC,CAAC,CAAC,CAAC,CAAC,CAAC,CAAC,CAAC,CAAC,CAAC,CAAC,CAAC,CAAC,CAAC,CAAC,CAAC,CAAC,CAAC,CAAC,CAAC,CAAC,CAAC,CAAC,CAAC,CAAC,CAAC,CAAC,CAAC,CAAC,CAAC,CAAC,CAAC,CAAC,CAAC,CAAC,CAAC,CAAC,CAAC,CAAC,CAAC,CAAC,CAAC,CAAC,CAAC,CAAC,CAAC,CAAC,CAAC,CAAC,CAAC,CAAC,CAAC,CAAC,CAAC,CAAC,CAAC,CAAC,CAAC,CAAC,CAAC,CAAC,CAAC,CAAC,CAAC,CAAC,CAAC,CAAC,CAAC,CAAC,CAAC,CAAC,CAAC,CAAC,CAAC,CAAC,CAAC,CAAC,CAAC,CAAC,CAAC,CAAC,CAAC,CAAC,CAAC,CAAC,CAAC,CAAC,CAAC,CAAC,CAAC,CAAC,CAAC,CAAC,CAAC,CAAC,CAAC,CAAC,CAAC,CAAC,CAAC,CAAC,CAAC,CAAC,CAAC,CAAC,CAAC,CAAC,CAAC,CAAC,CAAC,CAAC;AACxH,CAAC,CAAC,CAAC,CAAC,CAAC,CAAC,CAAC,CAAC,CAAC,CAAC,CAAC,CAAC,CAAC,CAAC,CAAC,CAAC,CAAC,CAAC,CAAC,CAAC,CAAC,CAAC,CAAC,CAAC,CAAC,CAAC,CAAC,CAAC,CAAC,CAAC,CAAC,CAAC,CAAC,CAAC,CAAC,CAAC,CAAC,CAAC,CAAC,CAAC,CAAC,CAAC,CAAC,CAAC,CAAC,CAAC,CAAC,CAAC,CAAC,CAAC,CAAC,CAAC,CAAC,CAAC,CAAC,CAAC,CAAC,CAAC,CAAC,CAAC;AAC5D,CAAC,CAAC,CAAC,CAAC,CAAC,CAAC,CAAC,CAAC,CAAC,CAAC,CAAC,CAAC,CAAC,CAAC,CAAC,CAAC,CAAC,CAAC,CAAC,CAAC,CAAC,CAAC,CAAC,CAAC,CAAC,CAAC,CAAC,CAAC,CAAC,CAAC,CAAC,CAAC,CAAC,CAAC,CAAC;AACnC,CAAC,CAAC,CAAC,CAAC,CAAC,CAAC,CAAC,CAAC,CAAC,CAAC,CAAC,CAAC,CAAC,CAAC,CAAC,CAAC,CAAC,CAAC,CAAC,CAAC,CAAC,CAAC,CAAC,CAAC,CAAC,CAAC,CAAC,CAAC,CAAC,CAAC,CAAC,CAAC,CAAC,CAAC,CAAC;AACnC,CAAC,CAAC,CAAC,CAAC,CAAC,CAAC,CAAC,CAAC,CAAC,CAAC,CAAC,CAAC,CAAC,CAAC,CAAC,CAAC,CAAC,CAAC,CAAC,CAAC,CAAC,CAAC,CAAC,CAAC,CAAC,CAAC,CAAC,CAAC,CAAC,CAAC,CAAC,CAAC,CAAC,CAAC,CAAC,CAAC,CAAC,CAAC,CAAC,CAAC,CAAC,CAAC,CAAC,CAAC;AAC5C,CAAC,CAAC,CAAC,CAAC,CAAC,CAAC,CAAC,CAAC,CAAC,CAAC,CAAC,CAAC,CAAC,CAAC,CAAC,CAAC,CAAC,CAAC,CAAC,CAAC,CAAC,CAAC,CAAC,CAAC,CAAC,CAAC,CAAC,CAAC,CAAC,CAAC,CAAC,CAAC,CAAC,CAAC,CAAC,CAAC,CAAC,CAAC,CAAC,CAAC,CAAC,CAAC,CAAC,CAAC,CAAC,CAAC,CAAC,CAAC,CAAC,CAAC,CAAC,CAAC,CAAC,CAAC,CAAC,CAAC,CAAC,CAAC,CAAC,CAAC,CAAC,CAAC,CAAC,CAAC,CAAC,CAAC,CAAC,CAAC,CAAC,CAAC,CAAC,CAAC,CAAC,CAAC,CAAC,CAAC,CAAC,CAAC,CAAC,CAAC,CAAC,CAAC,CAAC,CAAC,CAAC,CAAC,CAAC,CAAC,CAAC,CAAC,CAAC,CAAC,CAAC,CAAC,CAAC,CAAC,CAAC,CAAC,CAAC,CAAC,CAAC,CAAC,CAAC,CAAC,CAAC,CAAC,CAAC,CAAC,CAAC,CAAC,CAAC,CAAC,CAAC,CAAC,CAAC;AACnH,CAAC,CAAC,CAAC,CAAC,CAAC,CAAC,CAAC,CAAC,CAAC,CAAC,CAAC,CAAC,CAAC,CAAC,CAAC,CAAC,CAAC,CAAC,CAAC,CAAC,CAAC,CAAC,CAAC,CAAC,CAAC,CAAC,CAAC,CAAC,CAAC,CAAC,CAAC,CAAC,CAAC,CAAC,CAAC,CAAC,CAAC,CAAC,CAAC,CAAC,CAAC,CAAC,CAAC,CAAC,CAAC,CAAC,CAAC,CAAC,CAAC,CAAC,CAAC,CAAC,CAAC,CAAC;AACtD,CAAC,CAAC;AACF,CAAC,CAAC,CAAC,CAAC,CAAC,CAAC,CAAC,CAAC,CAAC,CAAC,CAAC,CAAC,CAAC,CAAC,CAAC,CAAC,CAAC,CAAC,CAAC,CAAC,CAAC,CAAC,CAAC,CAAC,CAAC,CAAC,CAAC,CAAC,CAAC,CAAC,CAAC,CAAC,CAAC,CAAC,CAAC,CAAC,CAAC,CAAC,CAAC,CAAC,CAAC,CAAC,CAAC,CAAC,CAAC,CAAC,CAAC,CAAC,CAAC,CAAC,CAAC,CAAC,CAAC;AACrD,CAAC,CAAC,CAAC,CAAC,CAAC,CAAC,CAAC,CAAC,CAAC,CAAC,CAAC,CAAC,CAAC,CAAC,CAAC,CAAC,CAAC,CAAC,CAAC,CAAC,CAAC,CAAC,CAAC,CAAC,CAAC,CAAC,CAAC,CAAC,CAAC,CAAC,CAAC,CAAC,CAAC,CAAC,CAAC,CAAC,CAAC,CAAC,CAAC,CAAC,CAAC,CAAC,CAAC,CAAC,CAAC,CAAC,CAAC,CAAC,CAAC,CAAC,CAAC,CAAC,CAAC,CAAC,CAAC,CAAC,CAAC,CAAC,CAAC,CAAC,CAAC,CAAC,CAAC,CAAC,CAAC,CAAC,CAAC,CAAC,CAAC,CAAC,CAAC,CAAC,CAAC,CAAC,CAAC,CAAC,CAAC,CAAC,CAAC,CAAC,CAAC,CAAC,CAAC,CAAC,CAAC,CAAC,CAAC,CAAC,CAAC,CAAC;"
      }
    },
    {
      "name": "nuxt:tree-shake-composables:transform",
      "start": 1756100544333,
      "end": 1756100544333,
      "order": "post"
    },
    {
      "name": "vite:build-import-analysis",
      "start": 1756100544333,
      "end": 1756100544333,
      "order": "normal"
    },
    {
      "name": "vite:reporter",
      "start": 1756100544333,
      "end": 1756100544333,
      "order": "normal"
    }
  ]
}
